{"participant":"robot7","clock":"unix_epoch","time_unit":"ms","t_start":1779382196827,"t_end":1779382317121,"stopped":true,"last_write_ms":1779382304142,"prover":[{"attestation_id":"attestationc47fe15ba4940171","dur_prover_e2e_ms":5286.9136,"dur_prover_e2e_ns":5286913599,"dur_prover_total_ms":5302.7324,"dur_prover_total_ns":5302732403,"dur_send_evidence_call_ms":15.3707,"dur_send_evidence_call_ns":15370712,"t_evidence_sent":1779382196840,"t_prover_finished":1779382202130,"t_prover_start":1779382196828,"t_result_received":1779382202127},{"attestation_id":"attestationee7d92d36e052cfc","dur_prover_e2e_ms":6698.2297,"dur_prover_e2e_ns":6698229726,"dur_prover_total_ms":6710.1886,"dur_prover_total_ns":6710188582,"dur_send_evidence_call_ms":8.4856,"dur_send_evidence_call_ns":8485644,"t_evidence_sent":1779382217352,"t_prover_finished":1779382224051,"t_prover_start":1779382217341,"t_result_received":1779382224050},{"attestation_id":"attestation61702d8559fe8b01","dur_prover_e2e_ms":2244.3631,"dur_prover_e2e_ns":2244363145,"dur_prover_total_ms":2259.3209,"dur_prover_total_ns":2259320873,"dur_send_evidence_call_ms":9.0703,"dur_send_evidence_call_ns":9070268,"t_evidence_sent":1779382237865,"t_prover_finished":1779382240111,"t_prover_start":1779382237852,"t_result_received":1779382240109},{"attestation_id":"attestation91fd7b43dd8962ff","dur_prover_e2e_ms":7712.1343,"dur_prover_e2e_ns":7712134259,"dur_prover_total_ms":7728.3804,"dur_prover_total_ns":7728380379,"dur_send_evidence_call_ms":7.965,"dur_send_evidence_call_ns":7964961,"t_evidence_sent":1779382258380,"t_prover_finished":1779382266094,"t_prover_start":1779382258366,"t_result_received":1779382266093},{"attestation_id":"attestation3599a719ee05500d","dur_prover_e2e_ms":7330.7184,"dur_prover_e2e_ns":7330718449,"dur_prover_total_ms":7346.3422,"dur_prover_total_ns":7346342209,"dur_send_evidence_call_ms":8.4287,"dur_send_evidence_call_ns":8428737,"t_evidence_sent":1779382278895,"t_prover_finished":1779382286228,"t_prover_start":1779382278881,"t_result_received":1779382286226},{"attestation_id":"attestatione467846408a15703","dur_prover_e2e_ms":4690.6251,"dur_prover_e2e_ns":4690625051,"dur_prover_total_ms":4706.2257,"dur_prover_total_ns":4706225675,"dur_send_evidence_call_ms":9.8647,"dur_send_evidence_call_ns":9864731,"t_evidence_sent":1779382299411,"t_prover_finished":1779382304103,"t_prover_start":1779382299397,"t_result_received":1779382304101}],"verifier":[{"attestation_id":"attestation4d185a52ce9d7b15","dur_send_result_call_ms":11.313,"dur_send_result_call_ns":11313010,"dur_signatures_fetch_ms":2.5214,"dur_signatures_fetch_ns":2521401,"dur_verifier_reaction_ms":3.1217,"dur_verifier_reaction_ns":3121709,"dur_verifier_total_ms":13.8769,"dur_verifier_total_ns":13876917,"dur_verify_compute_ms":0.001,"dur_verify_compute_ns":1024,"meta_verification_result":true,"t_get_signatures_finished":1779382240105,"t_get_signatures_start":1779382240103,"t_ready_for_evaluation_received":1779382240100,"t_result_sent":1779382240105,"t_verifier_finished":1779382240117,"t_verifier_start":1779382240103,"t_verify_compute_finished":1779382240105,"t_verify_compute_start":1779382240105},{"attestation_id":"attestation4704274fb9c4ed9f","dur_send_result_call_ms":10.238,"dur_send_result_call_ns":10237989,"dur_signatures_fetch_ms":2.1184,"dur_signatures_fetch_ns":2118434,"dur_verifier_reaction_ms":14.8443,"dur_verifier_reaction_ns":14844334,"dur_verifier_total_ms":12.3755,"dur_verifier_total_ns":12375485,"dur_verify_compute_ms":0.0016,"dur_verify_compute_ns":1579,"meta_verification_result":true,"t_get_signatures_finished":1779382240120,"t_get_signatures_start":1779382240118,"t_ready_for_evaluation_received":1779382240103,"t_result_sent":1779382240120,"t_verifier_finished":1779382240130,"t_verifier_start":1779382240117,"t_verify_compute_finished":1779382240120,"t_verify_compute_start":1779382240120},{"attestation_id":"attestation77b8b1123e8367fb","dur_send_result_call_ms":9.1096,"dur_send_result_call_ns":9109602,"dur_signatures_fetch_ms":2.0753,"dur_signatures_fetch_ns":2075290,"dur_verifier_reaction_ms":25.272,"dur_verifier_reaction_ns":25271976,"dur_verifier_total_ms":11.2167,"dur_verifier_total_ns":11216721,"dur_verify_compute_ms":0.003,"dur_verify_compute_ns":3021,"meta_verification_result":true,"t_get_signatures_finished":1779382240133,"t_get_signatures_start":1779382240131,"t_ready_for_evaluation_received":1779382240106,"t_result_sent":1779382240133,"t_verifier_finished":1779382240142,"t_verifier_start":1779382240131,"t_verify_compute_finished":1779382240133,"t_verify_compute_start":1779382240133},{"attestation_id":"attestationc0e2ceb8e8e51c14","dur_send_result_call_ms":10.4081,"dur_send_result_call_ns":10408054,"dur_signatures_fetch_ms":2.2004,"dur_signatures_fetch_ns":2200445,"dur_verifier_reaction_ms":34.4305,"dur_verifier_reaction_ns":34430471,"dur_verifier_total_ms":12.6402,"dur_verifier_total_ns":12640188,"dur_verify_compute_ms":0.0023,"dur_verify_compute_ns":2320,"meta_verification_result":true,"t_get_signatures_finished":1779382240145,"t_get_signatures_start":1779382240143,"t_ready_for_evaluation_received":1779382240108,"t_result_sent":1779382240145,"t_verifier_finished":1779382240155,"t_verifier_start":1779382240143,"t_verify_compute_finished":1779382240145,"t_verify_compute_start":1779382240145},{"attestation_id":"attestatione3eefef22f2cf16f","dur_send_result_call_ms":10.931,"dur_send_result_call_ns":10931018,"dur_signatures_fetch_ms":1.6036,"dur_signatures_fetch_ns":1603557,"dur_verifier_reaction_ms":44.5884,"dur_verifier_reaction_ns":44588392,"dur_verifier_total_ms":12.5602,"dur_verifier_total_ns":12560167,"dur_verify_compute_ms":0.0027,"dur_verify_compute_ns":2671,"meta_verification_result":true,"t_get_signatures_finished":1779382240158,"t_get_signatures_start":1779382240156,"t_ready_for_evaluation_received":1779382240112,"t_result_sent":1779382240158,"t_verifier_finished":1779382240169,"t_verifier_start":1779382240156,"t_verify_compute_finished":1779382240158,"t_verify_compute_start":1779382240158},{"attestation_id":"attestationc36b897fa5f2787a","dur_send_result_call_ms":9.7132,"dur_send_result_call_ns":9713190,"dur_signatures_fetch_ms":1.5795,"dur_signatures_fetch_ns":1579488,"dur_verifier_reaction_ms":53.2233,"dur_verifier_reaction_ns":53223291,"dur_verifier_total_ms":11.3144,"dur_verifier_total_ns":11314396,"dur_verify_compute_ms":0.0023,"dur_verify_compute_ns":2317,"meta_verification_result":true,"t_get_signatures_finished":1779382240171,"t_get_signatures_start":1779382240170,"t_ready_for_evaluation_received":1779382240116,"t_result_sent":1779382240171,"t_verifier_finished":1779382240181,"t_verifier_start":1779382240170,"t_verify_compute_finished":1779382240171,"t_verify_compute_start":1779382240171},{"attestation_id":"attestationb01a5b1217f8d3ab","dur_send_result_call_ms":10.8136,"dur_send_result_call_ns":10813550,"dur_signatures_fetch_ms":2.3273,"dur_signatures_fetch_ns":2327330,"dur_verifier_reaction_ms":61.0323,"dur_verifier_reaction_ns":61032297,"dur_verifier_total_ms":13.1637,"dur_verifier_total_ns":13163715,"dur_verify_compute_ms":0.0021,"dur_verify_compute_ns":2135,"meta_verification_result":true,"t_get_signatures_finished":1779382240185,"t_get_signatures_start":1779382240182,"t_ready_for_evaluation_received":1779382240121,"t_result_sent":1779382240185,"t_verifier_finished":1779382240195,"t_verifier_start":1779382240182,"t_verify_compute_finished":1779382240185,"t_verify_compute_start":1779382240185},{"attestation_id":"attestationd15da4627a628874","dur_send_result_call_ms":10.6816,"dur_send_result_call_ns":10681616,"dur_signatures_fetch_ms":2.0573,"dur_signatures_fetch_ns":2057261,"dur_verifier_reaction_ms":67.0892,"dur_verifier_reaction_ns":67089178,"dur_verifier_total_ms":12.7629,"dur_verifier_total_ns":12762934,"dur_verify_compute_ms":0.0016,"dur_verify_compute_ns":1603,"meta_verification_result":true,"t_get_signatures_finished":1779382240198,"t_get_signatures_start":1779382240196,"t_ready_for_evaluation_received":1779382240129,"t_result_sent":1779382240198,"t_verifier_finished":1779382240209,"t_verifier_start":1779382240196,"t_verify_compute_finished":1779382240198,"t_verify_compute_start":1779382240198},{"attestation_id":"attestation0c7532092b93baa8","dur_send_result_call_ms":9.2959,"dur_send_result_call_ns":9295895,"dur_signatures_fetch_ms":2.375,"dur_signatures_fetch_ns":2375044,"dur_verifier_reaction_ms":77.1172,"dur_verifier_reaction_ns":77117178,"dur_verifier_total_ms":11.6972,"dur_verifier_total_ns":11697235,"dur_verify_compute_ms":0.0015,"dur_verify_compute_ns":1547,"meta_verification_result":true,"t_get_signatures_finished":1779382240212,"t_get_signatures_start":1779382240210,"t_ready_for_evaluation_received":1779382240133,"t_result_sent":1779382240212,"t_verifier_finished":1779382240222,"t_verifier_start":1779382240210,"t_verify_compute_finished":1779382240212,"t_verify_compute_start":1779382240212},{"attestation_id":"attestation4e97a80c0a38bd7f","dur_send_result_call_ms":13.7165,"dur_send_result_call_ns":13716450,"dur_signatures_fetch_ms":1.2077,"dur_signatures_fetch_ns":1207675,"dur_verifier_reaction_ms":87.2161,"dur_verifier_reaction_ns":87216140,"dur_verifier_total_ms":14.9341,"dur_verifier_total_ns":14934083,"dur_verify_compute_ms":0.0007,"dur_verify_compute_ns":656,"meta_verification_result":true,"t_get_signatures_finished":1779382240224,"t_get_signatures_start":1779382240223,"t_ready_for_evaluation_received":1779382240136,"t_result_sent":1779382240224,"t_verifier_finished":1779382240238,"t_verifier_start":1779382240223,"t_verify_compute_finished":1779382240224,"t_verify_compute_start":1779382240224},{"attestation_id":"attestation3c335b4967ff1fce","dur_send_result_call_ms":13.434,"dur_send_result_call_ns":13433956,"dur_signatures_fetch_ms":1.7725,"dur_signatures_fetch_ns":1772541,"dur_verifier_reaction_ms":99.8212,"dur_verifier_reaction_ns":99821169,"dur_verifier_total_ms":15.221,"dur_verifier_total_ns":15221025,"dur_verify_compute_ms":0.0006,"dur_verify_compute_ns":637,"meta_verification_result":true,"t_get_signatures_finished":1779382240241,"t_get_signatures_start":1779382240239,"t_ready_for_evaluation_received":1779382240139,"t_result_sent":1779382240241,"t_verifier_finished":1779382240254,"t_verifier_start":1779382240239,"t_verify_compute_finished":1779382240241,"t_verify_compute_start":1779382240241},{"attestation_id":"attestatione884971322a8bd68","dur_send_result_call_ms":15.8194,"dur_send_result_call_ns":15819353,"dur_signatures_fetch_ms":1.5649,"dur_signatures_fetch_ns":1564930,"dur_verifier_reaction_ms":112.039,"dur_verifier_reaction_ns":112038988,"dur_verifier_total_ms":17.3926,"dur_verifier_total_ns":17392598,"dur_verify_compute_ms":0.0008,"dur_verify_compute_ns":750,"meta_verification_result":true,"t_get_signatures_finished":1779382240256,"t_get_signatures_start":1779382240255,"t_ready_for_evaluation_received":1779382240143,"t_result_sent":1779382240256,"t_verifier_finished":1779382240272,"t_verifier_start":1779382240255,"t_verify_compute_finished":1779382240256,"t_verify_compute_start":1779382240256},{"attestation_id":"attestation5984b5359c08da25","dur_send_result_call_ms":20.1586,"dur_send_result_call_ns":20158598,"dur_signatures_fetch_ms":1.7938,"dur_signatures_fetch_ns":1793838,"dur_verifier_reaction_ms":126.4347,"dur_verifier_reaction_ns":126434663,"dur_verifier_total_ms":21.9661,"dur_verifier_total_ns":21966140,"dur_verify_compute_ms":0.0013,"dur_verify_compute_ns":1263,"meta_verification_result":true,"t_get_signatures_finished":1779382240275,"t_get_signatures_start":1779382240273,"t_ready_for_evaluation_received":1779382240146,"t_result_sent":1779382240275,"t_verifier_finished":1779382240295,"t_verifier_start":1779382240273,"t_verify_compute_finished":1779382240275,"t_verify_compute_start":1779382240275},{"attestation_id":"attestation52204cd2080b9662","dur_send_result_call_ms":78.5831,"dur_send_result_call_ns":78583132,"dur_signatures_fetch_ms":1.4941,"dur_signatures_fetch_ns":1494055,"dur_verifier_reaction_ms":141.7058,"dur_verifier_reaction_ns":141705750,"dur_verifier_total_ms":80.0957,"dur_verifier_total_ns":80095691,"dur_verify_compute_ms":0.0015,"dur_verify_compute_ns":1464,"meta_verification_result":true,"t_get_signatures_finished":1779382240297,"t_get_signatures_start":1779382240296,"t_ready_for_evaluation_received":1779382240154,"t_result_sent":1779382240297,"t_verifier_finished":1779382240376,"t_verifier_start":1779382240296,"t_verify_compute_finished":1779382240297,"t_verify_compute_start":1779382240297},{"attestation_id":"attestatione107b48b5d58e446","dur_send_result_call_ms":8.3628,"dur_send_result_call_ns":8362839,"dur_signatures_fetch_ms":1.7967,"dur_signatures_fetch_ns":1796670,"dur_verifier_reaction_ms":219.9424,"dur_verifier_reaction_ns":219942415,"dur_verifier_total_ms":10.1808,"dur_verifier_total_ns":10180751,"dur_verify_compute_ms":0.0023,"dur_verify_compute_ns":2279,"meta_verification_result":true,"t_get_signatures_finished":1779382240378,"t_get_signatures_start":1779382240377,"t_ready_for_evaluation_received":1779382240157,"t_result_sent":1779382240378,"t_verifier_finished":1779382240387,"t_verifier_start":1779382240377,"t_verify_compute_finished":1779382240378,"t_verify_compute_start":1779382240378},{"attestation_id":"attestation215abcd13b7a0331","dur_send_result_call_ms":18.4666,"dur_send_result_call_ns":18466584,"dur_signatures_fetch_ms":2.2395,"dur_signatures_fetch_ns":2239492,"dur_verifier_reaction_ms":227.5028,"dur_verifier_reaction_ns":227502839,"dur_verifier_total_ms":20.7175,"dur_verifier_total_ns":20717454,"dur_verify_compute_ms":0.0008,"dur_verify_compute_ns":791,"meta_verification_result":true,"t_get_signatures_finished":1779382240390,"t_get_signatures_start":1779382240387,"t_ready_for_evaluation_received":1779382240160,"t_result_sent":1779382240390,"t_verifier_finished":1779382240408,"t_verifier_start":1779382240387,"t_verify_compute_finished":1779382240390,"t_verify_compute_start":1779382240390},{"attestation_id":"attestationce856b02a536b41d","dur_send_result_call_ms":8.1642,"dur_send_result_call_ns":8164198,"dur_signatures_fetch_ms":1.8822,"dur_signatures_fetch_ns":1882157,"dur_verifier_reaction_ms":246.0553,"dur_verifier_reaction_ns":246055291,"dur_verifier_total_ms":10.0615,"dur_verifier_total_ns":10061517,"dur_verify_compute_ms":0.0011,"dur_verify_compute_ns":1128,"meta_verification_result":true,"t_get_signatures_finished":1779382240411,"t_get_signatures_start":1779382240409,"t_ready_for_evaluation_received":1779382240163,"t_result_sent":1779382240411,"t_verifier_finished":1779382240419,"t_verifier_start":1779382240409,"t_verify_compute_finished":1779382240411,"t_verify_compute_start":1779382240411},{"attestation_id":"attestation8f6947042afa3904","dur_send_result_call_ms":11.2424,"dur_send_result_call_ns":11242436,"dur_signatures_fetch_ms":1.5548,"dur_signatures_fetch_ns":1554840,"dur_verifier_reaction_ms":253.1364,"dur_verifier_reaction_ns":253136387,"dur_verifier_total_ms":12.8157,"dur_verifier_total_ns":12815732,"dur_verify_compute_ms":0.002,"dur_verify_compute_ns":1996,"meta_verification_result":true,"t_get_signatures_finished":1779382240422,"t_get_signatures_start":1779382240420,"t_ready_for_evaluation_received":1779382240167,"t_result_sent":1779382240422,"t_verifier_finished":1779382240433,"t_verifier_start":1779382240420,"t_verify_compute_finished":1779382240422,"t_verify_compute_start":1779382240422},{"attestation_id":"attestation3ce1b03053a6969f","dur_send_result_call_ms":9.2412,"dur_send_result_call_ns":9241245,"dur_signatures_fetch_ms":1.4622,"dur_signatures_fetch_ns":1462222,"dur_verifier_reaction_ms":263.6178,"dur_verifier_reaction_ns":263617846,"dur_verifier_total_ms":10.725,"dur_verifier_total_ns":10725040,"dur_verify_compute_ms":0.0022,"dur_verify_compute_ns":2217,"meta_verification_result":true,"t_get_signatures_finished":1779382240435,"t_get_signatures_start":1779382240434,"t_ready_for_evaluation_received":1779382240170,"t_result_sent":1779382240435,"t_verifier_finished":1779382240444,"t_verifier_start":1779382240434,"t_verify_compute_finished":1779382240435,"t_verify_compute_start":1779382240435},{"attestation_id":"attestation5cb680c1b7c36136","dur_send_result_call_ms":10.2909,"dur_send_result_call_ns":10290881,"dur_signatures_fetch_ms":1.8901,"dur_signatures_fetch_ns":1890122,"dur_verifier_reaction_ms":271.6092,"dur_verifier_reaction_ns":271609157,"dur_verifier_total_ms":12.2002,"dur_verifier_total_ns":12200224,"dur_verify_compute_ms":0.0017,"dur_verify_compute_ns":1685,"meta_verification_result":true,"t_get_signatures_finished":1779382240447,"t_get_signatures_start":1779382240446,"t_ready_for_evaluation_received":1779382240174,"t_result_sent":1779382240447,"t_verifier_finished":1779382240458,"t_verifier_start":1779382240446,"t_verify_compute_finished":1779382240447,"t_verify_compute_start":1779382240447},{"attestation_id":"attestationb374ebd4c06feae8","dur_send_result_call_ms":8.213,"dur_send_result_call_ns":8212981,"dur_signatures_fetch_ms":2.1443,"dur_signatures_fetch_ns":2144255,"dur_verifier_reaction_ms":282.1232,"dur_verifier_reaction_ns":282123171,"dur_verifier_total_ms":10.3731,"dur_verifier_total_ns":10373138,"dur_verify_compute_ms":0.0013,"dur_verify_compute_ns":1287,"meta_verification_result":true,"t_get_signatures_finished":1779382240461,"t_get_signatures_start":1779382240459,"t_ready_for_evaluation_received":1779382240177,"t_result_sent":1779382240461,"t_verifier_finished":1779382240469,"t_verifier_start":1779382240459,"t_verify_compute_finished":1779382240461,"t_verify_compute_start":1779382240461},{"attestation_id":"attestation1568097cd50ab65e","dur_send_result_call_ms":8.1104,"dur_send_result_call_ns":8110415,"dur_signatures_fetch_ms":1.6558,"dur_signatures_fetch_ns":1655836,"dur_verifier_reaction_ms":289.9507,"dur_verifier_reaction_ns":289950720,"dur_verifier_total_ms":9.7866,"dur_verifier_total_ns":9786557,"dur_verify_compute_ms":0.0018,"dur_verify_compute_ns":1766,"meta_verification_result":true,"t_get_signatures_finished":1779382240472,"t_get_signatures_start":1779382240471,"t_ready_for_evaluation_received":1779382240181,"t_result_sent":1779382240472,"t_verifier_finished":1779382240480,"t_verifier_start":1779382240471,"t_verify_compute_finished":1779382240472,"t_verify_compute_start":1779382240472},{"attestation_id":"attestationc0991da9a9a04c03","dur_send_result_call_ms":8.0178,"dur_send_result_call_ns":8017834,"dur_signatures_fetch_ms":1.6954,"dur_signatures_fetch_ns":1695385,"dur_verifier_reaction_ms":297.2852,"dur_verifier_reaction_ns":297285207,"dur_verifier_total_ms":9.737,"dur_verifier_total_ns":9737037,"dur_verify_compute_ms":0.0016,"dur_verify_compute_ns":1640,"meta_verification_result":true,"t_get_signatures_finished":1779382240483,"t_get_signatures_start":1779382240482,"t_ready_for_evaluation_received":1779382240184,"t_result_sent":1779382240483,"t_verifier_finished":1779382240491,"t_verifier_start":1779382240482,"t_verify_compute_finished":1779382240483,"t_verify_compute_start":1779382240483},{"attestation_id":"attestation2811ea395062d058","dur_send_result_call_ms":8.0764,"dur_send_result_call_ns":8076385,"dur_signatures_fetch_ms":1.6985,"dur_signatures_fetch_ns":1698508,"dur_verifier_reaction_ms":300.9933,"dur_verifier_reaction_ns":300993252,"dur_verifier_total_ms":9.7983,"dur_verifier_total_ns":9798272,"dur_verify_compute_ms":0.0017,"dur_verify_compute_ns":1740,"meta_verification_result":true,"t_get_signatures_finished":1779382240495,"t_get_signatures_start":1779382240493,"t_ready_for_evaluation_received":1779382240192,"t_result_sent":1779382240495,"t_verifier_finished":1779382240503,"t_verifier_start":1779382240493,"t_verify_compute_finished":1779382240495,"t_verify_compute_start":1779382240495},{"attestation_id":"attestation9814346512fb4dd5","dur_send_result_call_ms":9.1667,"dur_send_result_call_ns":9166747,"dur_signatures_fetch_ms":1.9805,"dur_signatures_fetch_ns":1980541,"dur_verifier_reaction_ms":306.798,"dur_verifier_reaction_ns":306797960,"dur_verifier_total_ms":11.1688,"dur_verifier_total_ns":11168803,"dur_verify_compute_ms":0.0016,"dur_verify_compute_ns":1633,"meta_verification_result":true,"t_get_signatures_finished":1779382240507,"t_get_signatures_start":1779382240505,"t_ready_for_evaluation_received":1779382240198,"t_result_sent":1779382240507,"t_verifier_finished":1779382240516,"t_verifier_start":1779382240505,"t_verify_compute_finished":1779382240507,"t_verify_compute_start":1779382240507},{"attestation_id":"attestation87d22c84d0d0abc5","dur_send_result_call_ms":7.8324,"dur_send_result_call_ns":7832442,"dur_signatures_fetch_ms":1.7104,"dur_signatures_fetch_ns":1710432,"dur_verifier_reaction_ms":314.2651,"dur_verifier_reaction_ns":314265132,"dur_verifier_total_ms":9.5578,"dur_verifier_total_ns":9557805,"dur_verify_compute_ms":0.0018,"dur_verify_compute_ns":1752,"meta_verification_result":true,"t_get_signatures_finished":1779382240520,"t_get_signatures_start":1779382240518,"t_ready_for_evaluation_received":1779382240204,"t_result_sent":1779382240520,"t_verifier_finished":1779382240528,"t_verifier_start":1779382240518,"t_verify_compute_finished":1779382240520,"t_verify_compute_start":1779382240520},{"attestation_id":"attestationc7cb9337233d8ff8","dur_send_result_call_ms":7.7006,"dur_send_result_call_ns":7700584,"dur_signatures_fetch_ms":1.6473,"dur_signatures_fetch_ns":1647311,"dur_verifier_reaction_ms":322.248,"dur_verifier_reaction_ns":322247988,"dur_verifier_total_ms":9.3702,"dur_verifier_total_ns":9370190,"dur_verify_compute_ms":0.002,"dur_verify_compute_ns":2038,"meta_verification_result":true,"t_get_signatures_finished":1779382240532,"t_get_signatures_start":1779382240530,"t_ready_for_evaluation_received":1779382240208,"t_result_sent":1779382240532,"t_verifier_finished":1779382240539,"t_verifier_start":1779382240530,"t_verify_compute_finished":1779382240532,"t_verify_compute_start":1779382240532},{"attestation_id":"attestationa67e421cf28941cf","dur_send_result_call_ms":7.7761,"dur_send_result_call_ns":7776061,"dur_signatures_fetch_ms":1.7015,"dur_signatures_fetch_ns":1701531,"dur_verifier_reaction_ms":330.5212,"dur_verifier_reaction_ns":330521192,"dur_verifier_total_ms":9.4951,"dur_verifier_total_ns":9495095,"dur_verify_compute_ms":0.0016,"dur_verify_compute_ns":1576,"meta_verification_result":true,"t_get_signatures_finished":1779382240543,"t_get_signatures_start":1779382240541,"t_ready_for_evaluation_received":1779382240210,"t_result_sent":1779382240543,"t_verifier_finished":1779382240550,"t_verifier_start":1779382240541,"t_verify_compute_finished":1779382240543,"t_verify_compute_start":1779382240543},{"attestation_id":"attestation568d30646be93b07","dur_send_result_call_ms":7.4116,"dur_send_result_call_ns":7411649,"dur_signatures_fetch_ms":1.6859,"dur_signatures_fetch_ns":1685877,"dur_verifier_reaction_ms":334.2184,"dur_verifier_reaction_ns":334218402,"dur_verifier_total_ms":9.1151,"dur_verifier_total_ns":9115081,"dur_verify_compute_ms":0.0016,"dur_verify_compute_ns":1640,"meta_verification_result":true,"t_get_signatures_finished":1779382240554,"t_get_signatures_start":1779382240552,"t_ready_for_evaluation_received":1779382240218,"t_result_sent":1779382240554,"t_verifier_finished":1779382240561,"t_verifier_start":1779382240552,"t_verify_compute_finished":1779382240554,"t_verify_compute_start":1779382240554},{"attestation_id":"attestationb0f3dad1a64bea47","dur_send_result_call_ms":8.171,"dur_send_result_call_ns":8170964,"dur_signatures_fetch_ms":1.6474,"dur_signatures_fetch_ns":1647442,"dur_verifier_reaction_ms":2.6862,"dur_verifier_reaction_ns":2686211,"dur_verifier_total_ms":9.8556,"dur_verifier_total_ns":9855571,"dur_verify_compute_ms":0.0021,"dur_verify_compute_ns":2131,"meta_verification_result":true,"t_get_signatures_finished":1779382242259,"t_get_signatures_start":1779382242257,"t_ready_for_evaluation_received":1779382242255,"t_result_sent":1779382242259,"t_verifier_finished":1779382242267,"t_verifier_start":1779382242257,"t_verify_compute_finished":1779382242259,"t_verify_compute_start":1779382242259},{"attestation_id":"attestation7070881aadd898da","dur_send_result_call_ms":8.6036,"dur_send_result_call_ns":8603617,"dur_signatures_fetch_ms":1.9657,"dur_signatures_fetch_ns":1965699,"dur_verifier_reaction_ms":11.5213,"dur_verifier_reaction_ns":11521252,"dur_verifier_total_ms":10.6055,"dur_verifier_total_ns":10605493,"dur_verify_compute_ms":0.0017,"dur_verify_compute_ns":1673,"meta_verification_result":true,"t_get_signatures_finished":1779382242271,"t_get_signatures_start":1779382242269,"t_ready_for_evaluation_received":1779382242257,"t_result_sent":1779382242271,"t_verifier_finished":1779382242279,"t_verifier_start":1779382242269,"t_verify_compute_finished":1779382242271,"t_verify_compute_start":1779382242271},{"attestation_id":"attestationffbeb7fc7fcd58e9","dur_send_result_call_ms":15.4164,"dur_send_result_call_ns":15416412,"dur_signatures_fetch_ms":16.6839,"dur_signatures_fetch_ns":16683881,"dur_verifier_reaction_ms":36.597,"dur_verifier_reaction_ns":36596977,"dur_verifier_total_ms":32.2409,"dur_verifier_total_ns":32240915,"dur_verify_compute_ms":0.0026,"dur_verify_compute_ns":2632,"meta_verification_result":true,"t_get_signatures_finished":1779382302281,"t_get_signatures_start":1779382302264,"t_ready_for_evaluation_received":1779382302227,"t_result_sent":1779382302281,"t_verifier_finished":1779382302296,"t_verifier_start":1779382302264,"t_verify_compute_finished":1779382302281,"t_verify_compute_start":1779382302281},{"attestation_id":"attestationdd88db1fd6c76cba","dur_send_result_call_ms":15.2204,"dur_send_result_call_ns":15220401,"dur_signatures_fetch_ms":2.3075,"dur_signatures_fetch_ns":2307475,"dur_verifier_reaction_ms":34.3414,"dur_verifier_reaction_ns":34341424,"dur_verifier_total_ms":17.5394,"dur_verifier_total_ns":17539434,"dur_verify_compute_ms":0.0008,"dur_verify_compute_ns":832,"meta_verification_result":true,"t_get_signatures_finished":1779382302301,"t_get_signatures_start":1779382302298,"t_ready_for_evaluation_received":1779382302264,"t_result_sent":1779382302301,"t_verifier_finished":1779382302316,"t_verifier_start":1779382302298,"t_verify_compute_finished":1779382302301,"t_verify_compute_start":1779382302301},{"attestation_id":"attestation51f74614bbf20af7","dur_send_result_call_ms":19.0045,"dur_send_result_call_ns":19004456,"dur_signatures_fetch_ms":6.6109,"dur_signatures_fetch_ns":6610897,"dur_verifier_reaction_ms":33.1024,"dur_verifier_reaction_ns":33102374,"dur_verifier_total_ms":25.6451,"dur_verifier_total_ns":25645106,"dur_verify_compute_ms":0.0021,"dur_verify_compute_ns":2145,"meta_verification_result":true,"t_get_signatures_finished":1779382302324,"t_get_signatures_start":1779382302317,"t_ready_for_evaluation_received":1779382302284,"t_result_sent":1779382302324,"t_verifier_finished":1779382302343,"t_verifier_start":1779382302317,"t_verify_compute_finished":1779382302324,"t_verify_compute_start":1779382302324},{"attestation_id":"attestation8e7a49743045641a","dur_send_result_call_ms":22.8751,"dur_send_result_call_ns":22875135,"dur_signatures_fetch_ms":2.0704,"dur_signatures_fetch_ns":2070436,"dur_verifier_reaction_ms":55.9762,"dur_verifier_reaction_ns":55976230,"dur_verifier_total_ms":24.9755,"dur_verifier_total_ns":24975473,"dur_verify_compute_ms":0.0023,"dur_verify_compute_ns":2327,"meta_verification_result":true,"t_get_signatures_finished":1779382302347,"t_get_signatures_start":1779382302345,"t_ready_for_evaluation_received":1779382302289,"t_result_sent":1779382302347,"t_verifier_finished":1779382302370,"t_verifier_start":1779382302345,"t_verify_compute_finished":1779382302347,"t_verify_compute_start":1779382302347},{"attestation_id":"attestation2cfb81dec3d0c5b4","dur_send_result_call_ms":13.8187,"dur_send_result_call_ns":13818692,"dur_signatures_fetch_ms":2.1213,"dur_signatures_fetch_ns":2121312,"dur_verifier_reaction_ms":72.2816,"dur_verifier_reaction_ns":72281635,"dur_verifier_total_ms":15.9711,"dur_verifier_total_ns":15971129,"dur_verify_compute_ms":0.0023,"dur_verify_compute_ns":2335,"meta_verification_result":true,"t_get_signatures_finished":1779382302374,"t_get_signatures_start":1779382302372,"t_ready_for_evaluation_received":1779382302299,"t_result_sent":1779382302374,"t_verifier_finished":1779382302388,"t_verifier_start":1779382302372,"t_verify_compute_finished":1779382302374,"t_verify_compute_start":1779382302374},{"attestation_id":"attestation256bd2393acd3f4e","dur_send_result_call_ms":19.5272,"dur_send_result_call_ns":19527156,"dur_signatures_fetch_ms":3.1749,"dur_signatures_fetch_ns":3174932,"dur_verifier_reaction_ms":81.89,"dur_verifier_reaction_ns":81890014,"dur_verifier_total_ms":22.7211,"dur_verifier_total_ns":22721063,"dur_verify_compute_ms":0.0013,"dur_verify_compute_ns":1314,"meta_verification_result":true,"t_get_signatures_finished":1779382302392,"t_get_signatures_start":1779382302389,"t_ready_for_evaluation_received":1779382302307,"t_result_sent":1779382302392,"t_verifier_finished":1779382302412,"t_verifier_start":1779382302389,"t_verify_compute_finished":1779382302392,"t_verify_compute_start":1779382302392},{"attestation_id":"attestation03e87e1a32fc4fe0","dur_send_result_call_ms":12.4491,"dur_send_result_call_ns":12449094,"dur_signatures_fetch_ms":2.3926,"dur_signatures_fetch_ns":2392617,"dur_verifier_reaction_ms":103.1941,"dur_verifier_reaction_ns":103194118,"dur_verifier_total_ms":14.8573,"dur_verifier_total_ns":14857316,"dur_verify_compute_ms":0.0014,"dur_verify_compute_ns":1354,"meta_verification_result":true,"t_get_signatures_finished":1779382302416,"t_get_signatures_start":1779382302414,"t_ready_for_evaluation_received":1779382302310,"t_result_sent":1779382302416,"t_verifier_finished":1779382302429,"t_verifier_start":1779382302414,"t_verify_compute_finished":1779382302416,"t_verify_compute_start":1779382302416},{"attestation_id":"attestationfc5357df84947d65","dur_send_result_call_ms":13.7535,"dur_send_result_call_ns":13753455,"dur_signatures_fetch_ms":1.9116,"dur_signatures_fetch_ns":1911580,"dur_verifier_reaction_ms":106.4946,"dur_verifier_reaction_ns":106494597,"dur_verifier_total_ms":15.6802,"dur_verifier_total_ns":15680244,"dur_verify_compute_ms":0.0012,"dur_verify_compute_ns":1208,"meta_verification_result":true,"t_get_signatures_finished":1779382302432,"t_get_signatures_start":1779382302430,"t_ready_for_evaluation_received":1779382302323,"t_result_sent":1779382302432,"t_verifier_finished":1779382302446,"t_verifier_start":1779382302430,"t_verify_compute_finished":1779382302432,"t_verify_compute_start":1779382302432},{"attestation_id":"attestation935511e713422dd7","dur_send_result_call_ms":10.5458,"dur_send_result_call_ns":10545750,"dur_signatures_fetch_ms":1.452,"dur_signatures_fetch_ns":1452000,"dur_verifier_reaction_ms":105.5979,"dur_verifier_reaction_ns":105597942,"dur_verifier_total_ms":12.0099,"dur_verifier_total_ns":12009947,"dur_verify_compute_ms":0.0012,"dur_verify_compute_ns":1163,"meta_verification_result":true,"t_get_signatures_finished":1779382302448,"t_get_signatures_start":1779382302447,"t_ready_for_evaluation_received":1779382302341,"t_result_sent":1779382302448,"t_verifier_finished":1779382302459,"t_verifier_start":1779382302447,"t_verify_compute_finished":1779382302448,"t_verify_compute_start":1779382302448},{"attestation_id":"attestationa04e5be0a4735c74","dur_send_result_call_ms":7.2778,"dur_send_result_call_ns":7277752,"dur_signatures_fetch_ms":1.6442,"dur_signatures_fetch_ns":1644218,"dur_verifier_reaction_ms":113.5862,"dur_verifier_reaction_ns":113586227,"dur_verifier_total_ms":8.9326,"dur_verifier_total_ns":8932585,"dur_verify_compute_ms":0.0017,"dur_verify_compute_ns":1690,"meta_verification_result":true,"t_get_signatures_finished":1779382302462,"t_get_signatures_start":1779382302460,"t_ready_for_evaluation_received":1779382302346,"t_result_sent":1779382302462,"t_verifier_finished":1779382302469,"t_verifier_start":1779382302460,"t_verify_compute_finished":1779382302462,"t_verify_compute_start":1779382302462},{"attestation_id":"attestation415c2d57c28ff069","dur_send_result_call_ms":8.509,"dur_send_result_call_ns":8509009,"dur_signatures_fetch_ms":1.8628,"dur_signatures_fetch_ns":1862813,"dur_verifier_reaction_ms":119.8637,"dur_verifier_reaction_ns":119863661,"dur_verifier_total_ms":10.3841,"dur_verifier_total_ns":10384067,"dur_verify_compute_ms":0.0008,"dur_verify_compute_ns":812,"meta_verification_result":true,"t_get_signatures_finished":1779382302472,"t_get_signatures_start":1779382302470,"t_ready_for_evaluation_received":1779382302350,"t_result_sent":1779382302472,"t_verifier_finished":1779382302480,"t_verifier_start":1779382302470,"t_verify_compute_finished":1779382302472,"t_verify_compute_start":1779382302472},{"attestation_id":"attestationd1fc810cf849a312","dur_send_result_call_ms":9.8294,"dur_send_result_call_ns":9829412,"dur_signatures_fetch_ms":1.4143,"dur_signatures_fetch_ns":1414269,"dur_verifier_reaction_ms":112.3991,"dur_verifier_reaction_ns":112399114,"dur_verifier_total_ms":11.2562,"dur_verifier_total_ns":11256187,"dur_verify_compute_ms":0.0009,"dur_verify_compute_ns":897,"meta_verification_result":true,"t_get_signatures_finished":1779382302483,"t_get_signatures_start":1779382302481,"t_ready_for_evaluation_received":1779382302369,"t_result_sent":1779382302483,"t_verifier_finished":1779382302493,"t_verifier_start":1779382302481,"t_verify_compute_finished":1779382302483,"t_verify_compute_start":1779382302483},{"attestation_id":"attestation85b5f53bcb3d9ba2","dur_send_result_call_ms":7.3102,"dur_send_result_call_ns":7310184,"dur_signatures_fetch_ms":1.7676,"dur_signatures_fetch_ns":1767608,"dur_verifier_reaction_ms":121.0485,"dur_verifier_reaction_ns":121048517,"dur_verifier_total_ms":9.0985,"dur_verifier_total_ns":9098506,"dur_verify_compute_ms":0.0017,"dur_verify_compute_ns":1666,"meta_verification_result":true,"t_get_signatures_finished":1779382302496,"t_get_signatures_start":1779382302494,"t_ready_for_evaluation_received":1779382302373,"t_result_sent":1779382302496,"t_verifier_finished":1779382302503,"t_verifier_start":1779382302494,"t_verify_compute_finished":1779382302496,"t_verify_compute_start":1779382302496},{"attestation_id":"attestationb42b9be9534f57ce","dur_send_result_call_ms":7.4398,"dur_send_result_call_ns":7439819,"dur_signatures_fetch_ms":1.5641,"dur_signatures_fetch_ns":1564051,"dur_verifier_reaction_ms":127.1579,"dur_verifier_reaction_ns":127157869,"dur_verifier_total_ms":9.0249,"dur_verifier_total_ns":9024939,"dur_verify_compute_ms":0.0016,"dur_verify_compute_ns":1573,"meta_verification_result":true,"t_get_signatures_finished":1779382302506,"t_get_signatures_start":1779382302505,"t_ready_for_evaluation_received":1779382302378,"t_result_sent":1779382302506,"t_verifier_finished":1779382302514,"t_verifier_start":1779382302505,"t_verify_compute_finished":1779382302506,"t_verify_compute_start":1779382302506},{"attestation_id":"attestation3f98c16ff7652a30","dur_send_result_call_ms":6.9066,"dur_send_result_call_ns":6906568,"dur_signatures_fetch_ms":2.743,"dur_signatures_fetch_ns":2742955,"dur_verifier_reaction_ms":131.8838,"dur_verifier_reaction_ns":131883795,"dur_verifier_total_ms":9.6757,"dur_verifier_total_ns":9675679,"dur_verify_compute_ms":0.0024,"dur_verify_compute_ns":2399,"meta_verification_result":true,"t_get_signatures_finished":1779382302518,"t_get_signatures_start":1779382302515,"t_ready_for_evaluation_received":1779382302383,"t_result_sent":1779382302518,"t_verifier_finished":1779382302525,"t_verifier_start":1779382302515,"t_verify_compute_finished":1779382302518,"t_verify_compute_start":1779382302518},{"attestation_id":"attestation6385f56c1dad5e10","dur_send_result_call_ms":8.5779,"dur_send_result_call_ns":8577940,"dur_signatures_fetch_ms":1.6483,"dur_signatures_fetch_ns":1648266,"dur_verifier_reaction_ms":133.7235,"dur_verifier_reaction_ns":133723457,"dur_verifier_total_ms":10.2517,"dur_verifier_total_ns":10251735,"dur_verify_compute_ms":0.0022,"dur_verify_compute_ns":2231,"meta_verification_result":true,"t_get_signatures_finished":1779382302529,"t_get_signatures_start":1779382302528,"t_ready_for_evaluation_received":1779382302394,"t_result_sent":1779382302529,"t_verifier_finished":1779382302538,"t_verifier_start":1779382302528,"t_verify_compute_finished":1779382302529,"t_verify_compute_start":1779382302529},{"attestation_id":"attestation8358b63478ced141","dur_send_result_call_ms":8.4595,"dur_send_result_call_ns":8459524,"dur_signatures_fetch_ms":1.492,"dur_signatures_fetch_ns":1491987,"dur_verifier_reaction_ms":136.5957,"dur_verifier_reaction_ns":136595689,"dur_verifier_total_ms":9.977,"dur_verifier_total_ns":9976984,"dur_verify_compute_ms":0.0017,"dur_verify_compute_ns":1749,"meta_verification_result":true,"t_get_signatures_finished":1779382302541,"t_get_signatures_start":1779382302540,"t_ready_for_evaluation_received":1779382302403,"t_result_sent":1779382302541,"t_verifier_finished":1779382302550,"t_verifier_start":1779382302540,"t_verify_compute_finished":1779382302541,"t_verify_compute_start":1779382302541},{"attestation_id":"attestation7f77f415e4ad246b","dur_send_result_call_ms":10.0018,"dur_send_result_call_ns":10001775,"dur_signatures_fetch_ms":1.6449,"dur_signatures_fetch_ns":1644876,"dur_verifier_reaction_ms":143.0153,"dur_verifier_reaction_ns":143015348,"dur_verifier_total_ms":11.6711,"dur_verifier_total_ns":11671071,"dur_verify_compute_ms":0.0027,"dur_verify_compute_ns":2666,"meta_verification_result":true,"t_get_signatures_finished":1779382302554,"t_get_signatures_start":1779382302553,"t_ready_for_evaluation_received":1779382302410,"t_result_sent":1779382302554,"t_verifier_finished":1779382302564,"t_verifier_start":1779382302553,"t_verify_compute_finished":1779382302554,"t_verify_compute_start":1779382302554},{"attestation_id":"attestationd6f0faca4c09cf48","dur_send_result_call_ms":10.468,"dur_send_result_call_ns":10467994,"dur_signatures_fetch_ms":1.7719,"dur_signatures_fetch_ns":1771941,"dur_verifier_reaction_ms":151.6374,"dur_verifier_reaction_ns":151637371,"dur_verifier_total_ms":12.2701,"dur_verifier_total_ns":12270098,"dur_verify_compute_ms":0.0021,"dur_verify_compute_ns":2070,"meta_verification_result":true,"t_get_signatures_finished":1779382302569,"t_get_signatures_start":1779382302567,"t_ready_for_evaluation_received":1779382302416,"t_result_sent":1779382302569,"t_verifier_finished":1779382302580,"t_verifier_start":1779382302567,"t_verify_compute_finished":1779382302569,"t_verify_compute_start":1779382302569},{"attestation_id":"attestation97f1c5f136aef185","dur_send_result_call_ms":7.4017,"dur_send_result_call_ns":7401715,"dur_signatures_fetch_ms":1.4683,"dur_signatures_fetch_ns":1468313,"dur_verifier_reaction_ms":160.2667,"dur_verifier_reaction_ns":160266672,"dur_verifier_total_ms":8.8921,"dur_verifier_total_ns":8892052,"dur_verify_compute_ms":0.0017,"dur_verify_compute_ns":1733,"meta_verification_result":true,"t_get_signatures_finished":1779382302583,"t_get_signatures_start":1779382302582,"t_ready_for_evaluation_received":1779382302422,"t_result_sent":1779382302583,"t_verifier_finished":1779382302591,"t_verifier_start":1779382302582,"t_verify_compute_finished":1779382302583,"t_verify_compute_start":1779382302583},{"attestation_id":"attestation7596e74a5f9486ff","dur_send_result_call_ms":7.2311,"dur_send_result_call_ns":7231138,"dur_signatures_fetch_ms":2.1623,"dur_signatures_fetch_ns":2162302,"dur_verifier_reaction_ms":168.8596,"dur_verifier_reaction_ns":168859631,"dur_verifier_total_ms":9.4224,"dur_verifier_total_ns":9422392,"dur_verify_compute_ms":0.0023,"dur_verify_compute_ns":2314,"meta_verification_result":true,"t_get_signatures_finished":1779382302596,"t_get_signatures_start":1779382302593,"t_ready_for_evaluation_received":1779382302425,"t_result_sent":1779382302596,"t_verifier_finished":1779382302603,"t_verifier_start":1779382302593,"t_verify_compute_finished":1779382302596,"t_verify_compute_start":1779382302596},{"attestation_id":"attestationce69303096f8e86f","dur_send_result_call_ms":7.5851,"dur_send_result_call_ns":7585055,"dur_signatures_fetch_ms":1.4823,"dur_signatures_fetch_ns":1482302,"dur_verifier_reaction_ms":176.9314,"dur_verifier_reaction_ns":176931446,"dur_verifier_total_ms":9.088,"dur_verifier_total_ns":9087971,"dur_verify_compute_ms":0.0015,"dur_verify_compute_ns":1528,"meta_verification_result":true,"t_get_signatures_finished":1779382302606,"t_get_signatures_start":1779382302605,"t_ready_for_evaluation_received":1779382302428,"t_result_sent":1779382302606,"t_verifier_finished":1779382302614,"t_verifier_start":1779382302605,"t_verify_compute_finished":1779382302606,"t_verify_compute_start":1779382302606},{"attestation_id":"attestation1affee2a6acf8398","dur_send_result_call_ms":7.8496,"dur_send_result_call_ns":7849597,"dur_signatures_fetch_ms":2.0746,"dur_signatures_fetch_ns":2074565,"dur_verifier_reaction_ms":181.661,"dur_verifier_reaction_ns":181660981,"dur_verifier_total_ms":9.94,"dur_verifier_total_ns":9939981,"dur_verify_compute_ms":0.0011,"dur_verify_compute_ns":1059,"meta_verification_result":true,"t_get_signatures_finished":1779382302618,"t_get_signatures_start":1779382302616,"t_ready_for_evaluation_received":1779382302434,"t_result_sent":1779382302618,"t_verifier_finished":1779382302625,"t_verifier_start":1779382302616,"t_verify_compute_finished":1779382302618,"t_verify_compute_start":1779382302618},{"attestation_id":"attestation333d6e3b07c1b312","dur_send_result_call_ms":8.1723,"dur_send_result_call_ns":8172287,"dur_signatures_fetch_ms":1.5582,"dur_signatures_fetch_ns":1558225,"dur_verifier_reaction_ms":190.7791,"dur_verifier_reaction_ns":190779094,"dur_verifier_total_ms":9.7511,"dur_verifier_total_ns":9751052,"dur_verify_compute_ms":0.0016,"dur_verify_compute_ns":1593,"meta_verification_result":true,"t_get_signatures_finished":1779382302629,"t_get_signatures_start":1779382302627,"t_ready_for_evaluation_received":1779382302436,"t_result_sent":1779382302629,"t_verifier_finished":1779382302637,"t_verifier_start":1779382302627,"t_verify_compute_finished":1779382302629,"t_verify_compute_start":1779382302629},{"attestation_id":"attestation4f1c6bffbb35cae6","dur_send_result_call_ms":8.4726,"dur_send_result_call_ns":8472645,"dur_signatures_fetch_ms":1.8099,"dur_signatures_fetch_ns":1809884,"dur_verifier_reaction_ms":199.2637,"dur_verifier_reaction_ns":199263658,"dur_verifier_total_ms":10.2994,"dur_verifier_total_ns":10299374,"dur_verify_compute_ms":0.0013,"dur_verify_compute_ns":1335,"meta_verification_result":true,"t_get_signatures_finished":1779382302641,"t_get_signatures_start":1779382302639,"t_ready_for_evaluation_received":1779382302440,"t_result_sent":1779382302641,"t_verifier_finished":1779382302650,"t_verifier_start":1779382302639,"t_verify_compute_finished":1779382302641,"t_verify_compute_start":1779382302641},{"attestation_id":"attestationacdd3b2b1add830e","dur_send_result_call_ms":7.4115,"dur_send_result_call_ns":7411470,"dur_signatures_fetch_ms":1.8296,"dur_signatures_fetch_ns":1829563,"dur_verifier_reaction_ms":208.2558,"dur_verifier_reaction_ns":208255799,"dur_verifier_total_ms":9.2619,"dur_verifier_total_ns":9261850,"dur_verify_compute_ms":0.0016,"dur_verify_compute_ns":1584,"meta_verification_result":true,"t_get_signatures_finished":1779382302654,"t_get_signatures_start":1779382302652,"t_ready_for_evaluation_received":1779382302443,"t_result_sent":1779382302654,"t_verifier_finished":1779382302661,"t_verifier_start":1779382302652,"t_verify_compute_finished":1779382302654,"t_verify_compute_start":1779382302654},{"attestation_id":"attestationdca36a41e54abcd5","dur_send_result_call_ms":9.8403,"dur_send_result_call_ns":9840330,"dur_signatures_fetch_ms":1.5285,"dur_signatures_fetch_ns":1528549,"dur_verifier_reaction_ms":4.5381,"dur_verifier_reaction_ns":4538134,"dur_verifier_total_ms":11.4059,"dur_verifier_total_ns":11405900,"dur_verify_compute_ms":0.002,"dur_verify_compute_ns":1984,"meta_verification_result":true,"t_get_signatures_finished":1779382304079,"t_get_signatures_start":1779382304077,"t_ready_for_evaluation_received":1779382304073,"t_result_sent":1779382304079,"t_verifier_finished":1779382304089,"t_verifier_start":1779382304077,"t_verify_compute_finished":1779382304079,"t_verify_compute_start":1779382304079},{"attestation_id":"attestationa56921c6e599594a","dur_send_result_call_ms":8.1597,"dur_send_result_call_ns":8159678,"dur_signatures_fetch_ms":3.3452,"dur_signatures_fetch_ns":3345237,"dur_verifier_reaction_ms":16.1685,"dur_verifier_reaction_ns":16168537,"dur_verifier_total_ms":11.5353,"dur_verifier_total_ns":11535328,"dur_verify_compute_ms":0.0026,"dur_verify_compute_ns":2607,"meta_verification_result":true,"t_get_signatures_finished":1779382304097,"t_get_signatures_start":1779382304093,"t_ready_for_evaluation_received":1779382304077,"t_result_sent":1779382304097,"t_verifier_finished":1779382304105,"t_verifier_start":1779382304093,"t_verify_compute_finished":1779382304097,"t_verify_compute_start":1779382304097},{"attestation_id":"attestationd9833fdba2323dba","dur_send_result_call_ms":8.366,"dur_send_result_call_ns":8365974,"dur_signatures_fetch_ms":1.5132,"dur_signatures_fetch_ns":1513178,"dur_verifier_reaction_ms":26.0677,"dur_verifier_reaction_ns":26067749,"dur_verifier_total_ms":9.891,"dur_verifier_total_ns":9891010,"dur_verify_compute_ms":0.0012,"dur_verify_compute_ns":1234,"meta_verification_result":true,"t_get_signatures_finished":1779382304108,"t_get_signatures_start":1779382304107,"t_ready_for_evaluation_received":1779382304081,"t_result_sent":1779382304108,"t_verifier_finished":1779382304117,"t_verifier_start":1779382304107,"t_verify_compute_finished":1779382304108,"t_verify_compute_start":1779382304108},{"attestation_id":"attestation128a09f2817dfd23","dur_send_result_call_ms":8.5669,"dur_send_result_call_ns":8566855,"dur_signatures_fetch_ms":2.2212,"dur_signatures_fetch_ns":2221230,"dur_verifier_reaction_ms":32.3689,"dur_verifier_reaction_ns":32368932,"dur_verifier_total_ms":10.8068,"dur_verifier_total_ns":10806790,"dur_verify_compute_ms":0.0016,"dur_verify_compute_ns":1620,"meta_verification_result":true,"t_get_signatures_finished":1779382304120,"t_get_signatures_start":1779382304118,"t_ready_for_evaluation_received":1779382304086,"t_result_sent":1779382304120,"t_verifier_finished":1779382304129,"t_verifier_start":1779382304118,"t_verify_compute_finished":1779382304120,"t_verify_compute_start":1779382304120},{"attestation_id":"attestationc70cb82f087d9adb","dur_send_result_call_ms":8.9853,"dur_send_result_call_ns":8985266,"dur_signatures_fetch_ms":1.8887,"dur_signatures_fetch_ns":1888727,"dur_verifier_reaction_ms":41.1295,"dur_verifier_reaction_ns":41129522,"dur_verifier_total_ms":10.8938,"dur_verifier_total_ns":10893843,"dur_verify_compute_ms":0.0008,"dur_verify_compute_ns":786,"meta_verification_result":true,"t_get_signatures_finished":1779382304133,"t_get_signatures_start":1779382304131,"t_ready_for_evaluation_received":1779382304090,"t_result_sent":1779382304133,"t_verifier_finished":1779382304142,"t_verifier_start":1779382304131,"t_verify_compute_finished":1779382304133,"t_verify_compute_start":1779382304133}],"oracle":[]}
