{"participant":"robot8","clock":"unix_epoch","time_unit":"ms","t_start":1779382196826,"t_end":1779382317119,"stopped":true,"last_write_ms":1779382306115,"prover":[{"attestation_id":"attestation774c4379434817e4","dur_prover_e2e_ms":5286.659,"dur_prover_e2e_ns":5286659019,"dur_prover_total_ms":5301.6494,"dur_prover_total_ns":5301649420,"dur_send_evidence_call_ms":17.1738,"dur_send_evidence_call_ns":17173789,"t_evidence_sent":1779382196840,"t_prover_finished":1779382202129,"t_prover_start":1779382196827,"t_result_received":1779382202127},{"attestation_id":"attestatione89d46d7f0ca1213","dur_prover_e2e_ms":4883.9296,"dur_prover_e2e_ns":4883929592,"dur_prover_total_ms":4895.7513,"dur_prover_total_ns":4895751264,"dur_send_evidence_call_ms":15.3592,"dur_send_evidence_call_ns":15359249,"t_evidence_sent":1779382217353,"t_prover_finished":1779382222238,"t_prover_start":1779382217342,"t_result_received":1779382222237},{"attestation_id":"attestation9814346512fb4dd5","dur_prover_e2e_ms":4281.865,"dur_prover_e2e_ns":4281864963,"dur_prover_total_ms":4295.1444,"dur_prover_total_ns":4295144410,"dur_send_evidence_call_ms":18.7297,"dur_send_evidence_call_ns":18729688,"t_evidence_sent":1779382237866,"t_prover_finished":1779382242149,"t_prover_start":1779382237854,"t_result_received":1779382242148},{"attestation_id":"attestation103b5915a6c689f0","dur_prover_e2e_ms":7730.896,"dur_prover_e2e_ns":7730895971,"dur_prover_total_ms":7748.3032,"dur_prover_total_ns":7748303158,"dur_send_evidence_call_ms":17.7021,"dur_send_evidence_call_ns":17702130,"t_evidence_sent":1779382258383,"t_prover_finished":1779382266115,"t_prover_start":1779382258367,"t_result_received":1779382266113},{"attestation_id":"attestation34d9f0604bd52b76","dur_prover_e2e_ms":5293.7552,"dur_prover_e2e_ns":5293755165,"dur_prover_total_ms":5309.2142,"dur_prover_total_ns":5309214185,"dur_send_evidence_call_ms":13.6818,"dur_send_evidence_call_ns":13681849,"t_evidence_sent":1779382278895,"t_prover_finished":1779382284192,"t_prover_start":1779382278883,"t_result_received":1779382284189},{"attestation_id":"attestationd9833fdba2323dba","dur_prover_e2e_ms":6701.7527,"dur_prover_e2e_ns":6701752661,"dur_prover_total_ms":6717.3996,"dur_prover_total_ns":6717399629,"dur_send_evidence_call_ms":11.5569,"dur_send_evidence_call_ns":11556911,"t_evidence_sent":1779382299411,"t_prover_finished":1779382306115,"t_prover_start":1779382299397,"t_result_received":1779382306113}],"verifier":[],"oracle":[]}
