{"participant":"robot6","clock":"unix_epoch","time_unit":"ms","t_start":1782561796531,"t_end":1782561916995,"stopped":true,"last_write_ms":1782561911239,"prover":[{"attestation_id":"attestationa233aa6368e6e33b","dur_prover_e2e_ms":6527.2864,"dur_prover_e2e_ns":6527286394,"dur_prover_total_ms":6540.0801,"dur_prover_total_ns":6540080117,"dur_send_evidence_call_ms":29.5612,"dur_send_evidence_call_ns":29561207,"t_evidence_sent":1782561796544,"t_prover_finished":1782561803073,"t_prover_start":1782561796533,"t_result_received":1782561803071},{"attestation_id":"attestation38eaef9469c10483","dur_prover_e2e_ms":4677.4803,"dur_prover_e2e_ns":4677480291,"dur_prover_total_ms":4698.5152,"dur_prover_total_ns":4698515249,"dur_send_evidence_call_ms":19.3856,"dur_send_evidence_call_ns":19385585,"t_evidence_sent":1782561806564,"t_prover_finished":1782561811244,"t_prover_start":1782561806545,"t_result_received":1782561811242},{"attestation_id":"attestation6bf0f8ed517df1b6","dur_prover_e2e_ms":4679.5904,"dur_prover_e2e_ns":4679590360,"dur_prover_total_ms":4693.8574,"dur_prover_total_ns":4693857361,"dur_send_evidence_call_ms":13.1448,"dur_send_evidence_call_ns":13144838,"t_evidence_sent":1782561816578,"t_prover_finished":1782561821259,"t_prover_start":1782561816565,"t_result_received":1782561821257},{"attestation_id":"attestationc383ce2dfcaf9319","dur_prover_e2e_ms":4486.5894,"dur_prover_e2e_ns":4486589381,"dur_prover_total_ms":4499.5238,"dur_prover_total_ns":4499523756,"dur_send_evidence_call_ms":20.4124,"dur_send_evidence_call_ns":20412444,"t_evidence_sent":1782561826590,"t_prover_finished":1782561831079,"t_prover_start":1782561826579,"t_result_received":1782561831077},{"attestation_id":"attestation6adbc81eaea80535","dur_prover_e2e_ms":4489.2652,"dur_prover_e2e_ns":4489265235,"dur_prover_total_ms":4506.7952,"dur_prover_total_ns":4506795203,"dur_send_evidence_call_ms":25.4253,"dur_send_evidence_call_ns":25425260,"t_evidence_sent":1782561836606,"t_prover_finished":1782561841098,"t_prover_start":1782561836591,"t_result_received":1782561841096},{"attestation_id":"attestation6456c3c46f49413e","dur_prover_e2e_ms":4484.5021,"dur_prover_e2e_ns":4484502083,"dur_prover_total_ms":4505.3441,"dur_prover_total_ns":4505344105,"dur_send_evidence_call_ms":22.4183,"dur_send_evidence_call_ns":22418325,"t_evidence_sent":1782561846625,"t_prover_finished":1782561851112,"t_prover_start":1782561846607,"t_result_received":1782561851110},{"attestation_id":"attestation2db2671458db67b6","dur_prover_e2e_ms":6515.5913,"dur_prover_e2e_ns":6515591341,"dur_prover_total_ms":6527.2989,"dur_prover_total_ns":6527298909,"dur_send_evidence_call_ms":14.2202,"dur_send_evidence_call_ns":14220171,"t_evidence_sent":1782561856636,"t_prover_finished":1782561863153,"t_prover_start":1782561856626,"t_result_received":1782561863152},{"attestation_id":"attestation9a9d82eda5caa192","dur_prover_e2e_ms":2463.6856,"dur_prover_e2e_ns":2463685567,"dur_prover_total_ms":2482.2225,"dur_prover_total_ns":2482222543,"dur_send_evidence_call_ms":27.422,"dur_send_evidence_call_ns":27422007,"t_evidence_sent":1782561866654,"t_prover_finished":1782561869120,"t_prover_start":1782561866638,"t_result_received":1782561869118},{"attestation_id":"attestation1826dd19e555296a","dur_prover_e2e_ms":4482.5735,"dur_prover_e2e_ns":4482573486,"dur_prover_total_ms":4502.8871,"dur_prover_total_ns":4502887125,"dur_send_evidence_call_ms":24.8441,"dur_send_evidence_call_ns":24844147,"t_evidence_sent":1782561876674,"t_prover_finished":1782561881158,"t_prover_start":1782561876655,"t_result_received":1782561881156},{"attestation_id":"attestationd8cf9a3bd754aa30","dur_prover_e2e_ms":4490.5225,"dur_prover_e2e_ns":4490522462,"dur_prover_total_ms":4512.0749,"dur_prover_total_ns":4512074919,"dur_send_evidence_call_ms":22.8301,"dur_send_evidence_call_ns":22830131,"t_evidence_sent":1782561886690,"t_prover_finished":1782561891186,"t_prover_start":1782561886674,"t_result_received":1782561891181},{"attestation_id":"attestation46fba344ab74cc6e","dur_prover_e2e_ms":4483.5104,"dur_prover_e2e_ns":4483510400,"dur_prover_total_ms":4508.7355,"dur_prover_total_ns":4508735548,"dur_send_evidence_call_ms":20.3959,"dur_send_evidence_call_ns":20395917,"t_evidence_sent":1782561896714,"t_prover_finished":1782561901199,"t_prover_start":1782561896691,"t_result_received":1782561901197},{"attestation_id":"attestationf9a1634c593a0a4e","dur_prover_e2e_ms":4496.8815,"dur_prover_e2e_ns":4496881537,"dur_prover_total_ms":4525.265,"dur_prover_total_ns":4525264970,"dur_send_evidence_call_ms":31.8134,"dur_send_evidence_call_ns":31813378,"t_evidence_sent":1782561906736,"t_prover_finished":1782561911239,"t_prover_start":1782561906714,"t_result_received":1782561911233}],"verifier":[{"attestation_id":"attestation7cdc07a4459dfe99","dur_send_result_call_ms":19.0313,"dur_send_result_call_ns":19031323,"dur_signatures_fetch_ms":2.2283,"dur_signatures_fetch_ns":2228304,"dur_verifier_reaction_ms":3.6647,"dur_verifier_reaction_ns":3664731,"dur_verifier_total_ms":21.2914,"dur_verifier_total_ns":21291408,"dur_verify_compute_ms":0.0015,"dur_verify_compute_ns":1495,"meta_verification_result":true,"t_get_signatures_finished":1782561869138,"t_get_signatures_start":1782561869135,"t_ready_for_evaluation_received":1782561869132,"t_result_sent":1782561869138,"t_verifier_finished":1782561869157,"t_verifier_start":1782561869135,"t_verify_compute_finished":1782561869138,"t_verify_compute_start":1782561869138},{"attestation_id":"attestation083ad81ef89c7a78","dur_send_result_call_ms":19.6005,"dur_send_result_call_ns":19600512,"dur_signatures_fetch_ms":2.4107,"dur_signatures_fetch_ns":2410747,"dur_verifier_reaction_ms":21.939,"dur_verifier_reaction_ns":21938984,"dur_verifier_total_ms":22.0338,"dur_verifier_total_ns":22033796,"dur_verify_compute_ms":0.0022,"dur_verify_compute_ns":2202,"meta_verification_result":true,"t_get_signatures_finished":1782561869160,"t_get_signatures_start":1782561869157,"t_ready_for_evaluation_received":1782561869135,"t_result_sent":1782561869160,"t_verifier_finished":1782561869179,"t_verifier_start":1782561869157,"t_verify_compute_finished":1782561869160,"t_verify_compute_start":1782561869160},{"attestation_id":"attestation1eadb3fe0b54f8c7","dur_send_result_call_ms":21.0517,"dur_send_result_call_ns":21051703,"dur_signatures_fetch_ms":4.2349,"dur_signatures_fetch_ns":4234890,"dur_verifier_reaction_ms":39.3777,"dur_verifier_reaction_ns":39377674,"dur_verifier_total_ms":25.3148,"dur_verifier_total_ns":25314816,"dur_verify_compute_ms":0.0021,"dur_verify_compute_ns":2138,"meta_verification_result":true,"t_get_signatures_finished":1782561869185,"t_get_signatures_start":1782561869180,"t_ready_for_evaluation_received":1782561869141,"t_result_sent":1782561869185,"t_verifier_finished":1782561869206,"t_verifier_start":1782561869180,"t_verify_compute_finished":1782561869185,"t_verify_compute_start":1782561869185},{"attestation_id":"attestation986aa31b1eb1c25f","dur_send_result_call_ms":18.4323,"dur_send_result_call_ns":18432305,"dur_signatures_fetch_ms":4.2097,"dur_signatures_fetch_ns":4209650,"dur_verifier_reaction_ms":58.997,"dur_verifier_reaction_ns":58997028,"dur_verifier_total_ms":22.6657,"dur_verifier_total_ns":22665704,"dur_verify_compute_ms":0.002,"dur_verify_compute_ns":1959,"meta_verification_result":true,"t_get_signatures_finished":1782561869211,"t_get_signatures_start":1782561869207,"t_ready_for_evaluation_received":1782561869148,"t_result_sent":1782561869211,"t_verifier_finished":1782561869229,"t_verifier_start":1782561869207,"t_verify_compute_finished":1782561869211,"t_verify_compute_start":1782561869211},{"attestation_id":"attestation9e6e69d976547d00","dur_send_result_call_ms":30.5559,"dur_send_result_call_ns":30555900,"dur_signatures_fetch_ms":5.1189,"dur_signatures_fetch_ns":5118887,"dur_verifier_reaction_ms":76.7026,"dur_verifier_reaction_ns":76702564,"dur_verifier_total_ms":35.6992,"dur_verifier_total_ns":35699172,"dur_verify_compute_ms":0.0021,"dur_verify_compute_ns":2113,"meta_verification_result":true,"t_get_signatures_finished":1782561869235,"t_get_signatures_start":1782561869230,"t_ready_for_evaluation_received":1782561869154,"t_result_sent":1782561869235,"t_verifier_finished":1782561869266,"t_verifier_start":1782561869230,"t_verify_compute_finished":1782561869235,"t_verify_compute_start":1782561869235},{"attestation_id":"attestation6cc274d9a79c582b","dur_send_result_call_ms":19.6403,"dur_send_result_call_ns":19640310,"dur_signatures_fetch_ms":3.5077,"dur_signatures_fetch_ns":3507663,"dur_verifier_reaction_ms":107.6158,"dur_verifier_reaction_ns":107615760,"dur_verifier_total_ms":23.1697,"dur_verifier_total_ns":23169658,"dur_verify_compute_ms":0.0021,"dur_verify_compute_ns":2075,"meta_verification_result":true,"t_get_signatures_finished":1782561869271,"t_get_signatures_start":1782561869267,"t_ready_for_evaluation_received":1782561869159,"t_result_sent":1782561869271,"t_verifier_finished":1782561869290,"t_verifier_start":1782561869267,"t_verify_compute_finished":1782561869271,"t_verify_compute_start":1782561869271},{"attestation_id":"attestation66a4ccdfa56f969b","dur_send_result_call_ms":14.7786,"dur_send_result_call_ns":14778588,"dur_signatures_fetch_ms":2.1345,"dur_signatures_fetch_ns":2134545,"dur_verifier_reaction_ms":127.37,"dur_verifier_reaction_ns":127369989,"dur_verifier_total_ms":16.9234,"dur_verifier_total_ns":16923355,"dur_verify_compute_ms":0.0008,"dur_verify_compute_ns":812,"meta_verification_result":true,"t_get_signatures_finished":1782561869293,"t_get_signatures_start":1782561869291,"t_ready_for_evaluation_received":1782561869164,"t_result_sent":1782561869293,"t_verifier_finished":1782561869308,"t_verifier_start":1782561869291,"t_verify_compute_finished":1782561869293,"t_verify_compute_start":1782561869293},{"attestation_id":"attestation6c898dc7f66b735a","dur_send_result_call_ms":13.4448,"dur_send_result_call_ns":13444840,"dur_signatures_fetch_ms":1.5664,"dur_signatures_fetch_ns":1566370,"dur_verifier_reaction_ms":139.193,"dur_verifier_reaction_ns":139192964,"dur_verifier_total_ms":15.0275,"dur_verifier_total_ns":15027525,"dur_verify_compute_ms":0.0074,"dur_verify_compute_ns":7354,"meta_verification_result":true,"t_get_signatures_finished":1782561869310,"t_get_signatures_start":1782561869309,"t_ready_for_evaluation_received":1782561869170,"t_result_sent":1782561869310,"t_verifier_finished":1782561869324,"t_verifier_start":1782561869309,"t_verify_compute_finished":1782561869310,"t_verify_compute_start":1782561869310},{"attestation_id":"attestation3890999bc1d0c1a1","dur_send_result_call_ms":13.9423,"dur_send_result_call_ns":13942308,"dur_signatures_fetch_ms":1.7815,"dur_signatures_fetch_ns":1781459,"dur_verifier_reaction_ms":147.8413,"dur_verifier_reaction_ns":147841274,"dur_verifier_total_ms":15.7414,"dur_verifier_total_ns":15741368,"dur_verify_compute_ms":0.0006,"dur_verify_compute_ns":637,"meta_verification_result":true,"t_get_signatures_finished":1782561869326,"t_get_signatures_start":1782561869324,"t_ready_for_evaluation_received":1782561869177,"t_result_sent":1782561869326,"t_verifier_finished":1782561869340,"t_verifier_start":1782561869324,"t_verify_compute_finished":1782561869326,"t_verify_compute_start":1782561869326},{"attestation_id":"attestationc28bcecbe88da3a4","dur_send_result_call_ms":10.1376,"dur_send_result_call_ns":10137600,"dur_signatures_fetch_ms":1.6667,"dur_signatures_fetch_ns":1666657,"dur_verifier_reaction_ms":157.2274,"dur_verifier_reaction_ns":157227436,"dur_verifier_total_ms":11.8146,"dur_verifier_total_ns":11814572,"dur_verify_compute_ms":0.0007,"dur_verify_compute_ns":715,"meta_verification_result":true,"t_get_signatures_finished":1782561869342,"t_get_signatures_start":1782561869341,"t_ready_for_evaluation_received":1782561869183,"t_result_sent":1782561869342,"t_verifier_finished":1782561869352,"t_verifier_start":1782561869341,"t_verify_compute_finished":1782561869342,"t_verify_compute_start":1782561869342},{"attestation_id":"attestationae27a0f7867e5399","dur_send_result_call_ms":9.9921,"dur_send_result_call_ns":9992130,"dur_signatures_fetch_ms":1.9753,"dur_signatures_fetch_ns":1975273,"dur_verifier_reaction_ms":161.4493,"dur_verifier_reaction_ns":161449265,"dur_verifier_total_ms":11.9898,"dur_verifier_total_ns":11989794,"dur_verify_compute_ms":0.0018,"dur_verify_compute_ns":1842,"meta_verification_result":true,"t_get_signatures_finished":1782561869356,"t_get_signatures_start":1782561869354,"t_ready_for_evaluation_received":1782561869192,"t_result_sent":1782561869356,"t_verifier_finished":1782561869366,"t_verifier_start":1782561869354,"t_verify_compute_finished":1782561869356,"t_verify_compute_start":1782561869356},{"attestation_id":"attestationf44cb8c2a30f7da6","dur_send_result_call_ms":9.5397,"dur_send_result_call_ns":9539709,"dur_signatures_fetch_ms":2.0214,"dur_signatures_fetch_ns":2021444,"dur_verifier_reaction_ms":168.2475,"dur_verifier_reaction_ns":168247525,"dur_verifier_total_ms":11.5859,"dur_verifier_total_ns":11585944,"dur_verify_compute_ms":0.0018,"dur_verify_compute_ns":1755,"meta_verification_result":true,"t_get_signatures_finished":1782561869369,"t_get_signatures_start":1782561869367,"t_ready_for_evaluation_received":1782561869199,"t_result_sent":1782561869369,"t_verifier_finished":1782561869379,"t_verifier_start":1782561869367,"t_verify_compute_finished":1782561869369,"t_verify_compute_start":1782561869369},{"attestation_id":"attestationbe9e912eb6f7d617","dur_send_result_call_ms":11.3693,"dur_send_result_call_ns":11369311,"dur_signatures_fetch_ms":1.6437,"dur_signatures_fetch_ns":1643705,"dur_verifier_reaction_ms":174.8738,"dur_verifier_reaction_ns":174873761,"dur_verifier_total_ms":13.0284,"dur_verifier_total_ns":13028445,"dur_verify_compute_ms":0.0016,"dur_verify_compute_ns":1564,"meta_verification_result":true,"t_get_signatures_finished":1782561869381,"t_get_signatures_start":1782561869380,"t_ready_for_evaluation_received":1782561869205,"t_result_sent":1782561869381,"t_verifier_finished":1782561869393,"t_verifier_start":1782561869380,"t_verify_compute_finished":1782561869381,"t_verify_compute_start":1782561869381},{"attestation_id":"attestationf188dafb8f39d75a","dur_send_result_call_ms":10.7393,"dur_send_result_call_ns":10739313,"dur_signatures_fetch_ms":1.6331,"dur_signatures_fetch_ns":1633143,"dur_verifier_reaction_ms":181.9086,"dur_verifier_reaction_ns":181908554,"dur_verifier_total_ms":12.3923,"dur_verifier_total_ns":12392275,"dur_verify_compute_ms":0.0015,"dur_verify_compute_ns":1502,"meta_verification_result":true,"t_get_signatures_finished":1782561869396,"t_get_signatures_start":1782561869395,"t_ready_for_evaluation_received":1782561869213,"t_result_sent":1782561869396,"t_verifier_finished":1782561869407,"t_verifier_start":1782561869395,"t_verify_compute_finished":1782561869396,"t_verify_compute_start":1782561869396},{"attestation_id":"attestation4b7bb60178a8b96a","dur_send_result_call_ms":10.3838,"dur_send_result_call_ns":10383831,"dur_signatures_fetch_ms":1.8671,"dur_signatures_fetch_ns":1867085,"dur_verifier_reaction_ms":190.6646,"dur_verifier_reaction_ns":190664598,"dur_verifier_total_ms":12.276,"dur_verifier_total_ns":12275974,"dur_verify_compute_ms":0.0017,"dur_verify_compute_ns":1666,"meta_verification_result":true,"t_get_signatures_finished":1782561869410,"t_get_signatures_start":1782561869408,"t_ready_for_evaluation_received":1782561869218,"t_result_sent":1782561869410,"t_verifier_finished":1782561869421,"t_verifier_start":1782561869408,"t_verify_compute_finished":1782561869410,"t_verify_compute_start":1782561869410},{"attestation_id":"attestation6dd48e4ddbecefbf","dur_send_result_call_ms":11.6331,"dur_send_result_call_ns":11633141,"dur_signatures_fetch_ms":2.0386,"dur_signatures_fetch_ns":2038557,"dur_verifier_reaction_ms":198.5321,"dur_verifier_reaction_ns":198532125,"dur_verifier_total_ms":13.6951,"dur_verifier_total_ns":13695135,"dur_verify_compute_ms":0.0017,"dur_verify_compute_ns":1743,"meta_verification_result":true,"t_get_signatures_finished":1782561869424,"t_get_signatures_start":1782561869422,"t_ready_for_evaluation_received":1782561869223,"t_result_sent":1782561869424,"t_verifier_finished":1782561869436,"t_verifier_start":1782561869422,"t_verify_compute_finished":1782561869424,"t_verify_compute_start":1782561869424},{"attestation_id":"attestation9164eddb5e94042b","dur_send_result_call_ms":11.0561,"dur_send_result_call_ns":11056110,"dur_signatures_fetch_ms":1.6704,"dur_signatures_fetch_ns":1670392,"dur_verifier_reaction_ms":208.2972,"dur_verifier_reaction_ns":208297179,"dur_verifier_total_ms":12.7591,"dur_verifier_total_ns":12759110,"dur_verify_compute_ms":0.0019,"dur_verify_compute_ns":1855,"meta_verification_result":true,"t_get_signatures_finished":1782561869439,"t_get_signatures_start":1782561869437,"t_ready_for_evaluation_received":1782561869229,"t_result_sent":1782561869439,"t_verifier_finished":1782561869450,"t_verifier_start":1782561869437,"t_verify_compute_finished":1782561869439,"t_verify_compute_start":1782561869439},{"attestation_id":"attestationaea1baa12bbd5f76","dur_send_result_call_ms":12.1006,"dur_send_result_call_ns":12100592,"dur_signatures_fetch_ms":2.1975,"dur_signatures_fetch_ns":2197529,"dur_verifier_reaction_ms":214.398,"dur_verifier_reaction_ns":214398024,"dur_verifier_total_ms":14.3218,"dur_verifier_total_ns":14321750,"dur_verify_compute_ms":0.0016,"dur_verify_compute_ns":1584,"meta_verification_result":true,"t_get_signatures_finished":1782561869453,"t_get_signatures_start":1782561869451,"t_ready_for_evaluation_received":1782561869237,"t_result_sent":1782561869453,"t_verifier_finished":1782561869465,"t_verifier_start":1782561869451,"t_verify_compute_finished":1782561869453,"t_verify_compute_start":1782561869453},{"attestation_id":"attestationb153d09d34131322","dur_send_result_call_ms":12.6535,"dur_send_result_call_ns":12653523,"dur_signatures_fetch_ms":1.9083,"dur_signatures_fetch_ns":1908348,"dur_verifier_reaction_ms":225.1695,"dur_verifier_reaction_ns":225169520,"dur_verifier_total_ms":14.5903,"dur_verifier_total_ns":14590337,"dur_verify_compute_ms":0.0016,"dur_verify_compute_ns":1631,"meta_verification_result":true,"t_get_signatures_finished":1782561869469,"t_get_signatures_start":1782561869467,"t_ready_for_evaluation_received":1782561869242,"t_result_sent":1782561869469,"t_verifier_finished":1782561869482,"t_verifier_start":1782561869467,"t_verify_compute_finished":1782561869469,"t_verify_compute_start":1782561869469},{"attestation_id":"attestation01d4ffe38a2dae4c","dur_send_result_call_ms":13.1653,"dur_send_result_call_ns":13165332,"dur_signatures_fetch_ms":2.4018,"dur_signatures_fetch_ns":2401828,"dur_verifier_reaction_ms":226.6173,"dur_verifier_reaction_ns":226617288,"dur_verifier_total_ms":15.59,"dur_verifier_total_ns":15590032,"dur_verify_compute_ms":0.0017,"dur_verify_compute_ns":1704,"meta_verification_result":true,"t_get_signatures_finished":1782561869485,"t_get_signatures_start":1782561869483,"t_ready_for_evaluation_received":1782561869256,"t_result_sent":1782561869485,"t_verifier_finished":1782561869499,"t_verifier_start":1782561869483,"t_verify_compute_finished":1782561869485,"t_verify_compute_start":1782561869485},{"attestation_id":"attestatione8db2e3ac1f68328","dur_send_result_call_ms":11.1522,"dur_send_result_call_ns":11152153,"dur_signatures_fetch_ms":1.813,"dur_signatures_fetch_ns":1813034,"dur_verifier_reaction_ms":236.6759,"dur_verifier_reaction_ns":236675949,"dur_verifier_total_ms":12.9849,"dur_verifier_total_ns":12984905,"dur_verify_compute_ms":0.0017,"dur_verify_compute_ns":1659,"meta_verification_result":true,"t_get_signatures_finished":1782561869502,"t_get_signatures_start":1782561869500,"t_ready_for_evaluation_received":1782561869264,"t_result_sent":1782561869502,"t_verifier_finished":1782561869513,"t_verifier_start":1782561869500,"t_verify_compute_finished":1782561869502,"t_verify_compute_start":1782561869502},{"attestation_id":"attestationd8a2eb140a7b5c74","dur_send_result_call_ms":11.9307,"dur_send_result_call_ns":11930660,"dur_signatures_fetch_ms":1.7699,"dur_signatures_fetch_ns":1769870,"dur_verifier_reaction_ms":245.2611,"dur_verifier_reaction_ns":245261068,"dur_verifier_total_ms":13.7267,"dur_verifier_total_ns":13726713,"dur_verify_compute_ms":0.0017,"dur_verify_compute_ns":1744,"meta_verification_result":true,"t_get_signatures_finished":1782561869517,"t_get_signatures_start":1782561869516,"t_ready_for_evaluation_received":1782561869270,"t_result_sent":1782561869517,"t_verifier_finished":1782561869529,"t_verifier_start":1782561869516,"t_verify_compute_finished":1782561869517,"t_verify_compute_start":1782561869517},{"attestation_id":"attestation2186e5c1be2f7ff3","dur_send_result_call_ms":11.2113,"dur_send_result_call_ns":11211303,"dur_signatures_fetch_ms":1.902,"dur_signatures_fetch_ns":1902006,"dur_verifier_reaction_ms":255.813,"dur_verifier_reaction_ns":255813013,"dur_verifier_total_ms":13.1449,"dur_verifier_total_ns":13144906,"dur_verify_compute_ms":0.0017,"dur_verify_compute_ns":1732,"meta_verification_result":true,"t_get_signatures_finished":1782561869534,"t_get_signatures_start":1782561869532,"t_ready_for_evaluation_received":1782561869276,"t_result_sent":1782561869534,"t_verifier_finished":1782561869545,"t_verifier_start":1782561869532,"t_verify_compute_finished":1782561869534,"t_verify_compute_start":1782561869534},{"attestation_id":"attestation15621653237b669a","dur_send_result_call_ms":14.5781,"dur_send_result_call_ns":14578092,"dur_signatures_fetch_ms":1.6624,"dur_signatures_fetch_ns":1662418,"dur_verifier_reaction_ms":265.9248,"dur_verifier_reaction_ns":265924767,"dur_verifier_total_ms":16.2608,"dur_verifier_total_ns":16260805,"dur_verify_compute_ms":0.0017,"dur_verify_compute_ns":1664,"meta_verification_result":true,"t_get_signatures_finished":1782561869549,"t_get_signatures_start":1782561869547,"t_ready_for_evaluation_received":1782561869281,"t_result_sent":1782561869549,"t_verifier_finished":1782561869563,"t_verifier_start":1782561869547,"t_verify_compute_finished":1782561869549,"t_verify_compute_start":1782561869549},{"attestation_id":"attestationf2e5596ef0a2e0fd","dur_send_result_call_ms":10.1763,"dur_send_result_call_ns":10176304,"dur_signatures_fetch_ms":1.6604,"dur_signatures_fetch_ns":1660356,"dur_verifier_reaction_ms":279.4632,"dur_verifier_reaction_ns":279463182,"dur_verifier_total_ms":11.8675,"dur_verifier_total_ns":11867484,"dur_verify_compute_ms":0.002,"dur_verify_compute_ns":2041,"meta_verification_result":true,"t_get_signatures_finished":1782561869566,"t_get_signatures_start":1782561869565,"t_ready_for_evaluation_received":1782561869285,"t_result_sent":1782561869566,"t_verifier_finished":1782561869576,"t_verifier_start":1782561869565,"t_verify_compute_finished":1782561869566,"t_verify_compute_start":1782561869566},{"attestation_id":"attestation7d1076e966294b6e","dur_send_result_call_ms":19.173,"dur_send_result_call_ns":19173037,"dur_signatures_fetch_ms":3.4885,"dur_signatures_fetch_ns":3488524,"dur_verifier_reaction_ms":3.258,"dur_verifier_reaction_ns":3258042,"dur_verifier_total_ms":22.7027,"dur_verifier_total_ns":22702670,"dur_verify_compute_ms":0.0044,"dur_verify_compute_ns":4419,"meta_verification_result":true,"t_get_signatures_finished":1782561871129,"t_get_signatures_start":1782561871125,"t_ready_for_evaluation_received":1782561871122,"t_result_sent":1782561871129,"t_verifier_finished":1782561871148,"t_verifier_start":1782561871125,"t_verify_compute_finished":1782561871129,"t_verify_compute_start":1782561871129},{"attestation_id":"attestation163c89c9fd0b93d8","dur_send_result_call_ms":16.4637,"dur_send_result_call_ns":16463651,"dur_signatures_fetch_ms":3.4239,"dur_signatures_fetch_ns":3423912,"dur_verifier_reaction_ms":23.5659,"dur_verifier_reaction_ns":23565895,"dur_verifier_total_ms":19.909,"dur_verifier_total_ns":19908951,"dur_verify_compute_ms":0.0022,"dur_verify_compute_ns":2157,"meta_verification_result":true,"t_get_signatures_finished":1782561871152,"t_get_signatures_start":1782561871149,"t_ready_for_evaluation_received":1782561871125,"t_result_sent":1782561871152,"t_verifier_finished":1782561871169,"t_verifier_start":1782561871149,"t_verify_compute_finished":1782561871152,"t_verify_compute_start":1782561871152},{"attestation_id":"attestation629a5bdd29123294","dur_send_result_call_ms":14.1816,"dur_send_result_call_ns":14181592,"dur_signatures_fetch_ms":1.8426,"dur_signatures_fetch_ns":1842557,"dur_verifier_reaction_ms":38.5001,"dur_verifier_reaction_ns":38500124,"dur_verifier_total_ms":16.0521,"dur_verifier_total_ns":16052099,"dur_verify_compute_ms":0.0007,"dur_verify_compute_ns":694,"meta_verification_result":true,"t_get_signatures_finished":1782561871171,"t_get_signatures_start":1782561871169,"t_ready_for_evaluation_received":1782561871131,"t_result_sent":1782561871171,"t_verifier_finished":1782561871186,"t_verifier_start":1782561871169,"t_verify_compute_finished":1782561871171,"t_verify_compute_start":1782561871171},{"attestation_id":"attestation6cf3f906c97c3186","dur_send_result_call_ms":11.7552,"dur_send_result_call_ns":11755157,"dur_signatures_fetch_ms":1.917,"dur_signatures_fetch_ns":1917039,"dur_verifier_reaction_ms":50.9001,"dur_verifier_reaction_ns":50900101,"dur_verifier_total_ms":13.6834,"dur_verifier_total_ns":13683392,"dur_verify_compute_ms":0.0008,"dur_verify_compute_ns":802,"meta_verification_result":true,"t_get_signatures_finished":1782561871188,"t_get_signatures_start":1782561871186,"t_ready_for_evaluation_received":1782561871136,"t_result_sent":1782561871188,"t_verifier_finished":1782561871200,"t_verifier_start":1782561871186,"t_verify_compute_finished":1782561871188,"t_verify_compute_start":1782561871188},{"attestation_id":"attestation08e4b383ad1a6ae3","dur_send_result_call_ms":9.7862,"dur_send_result_call_ns":9786185,"dur_signatures_fetch_ms":1.9872,"dur_signatures_fetch_ns":1987150,"dur_verifier_reaction_ms":61.6787,"dur_verifier_reaction_ns":61678734,"dur_verifier_total_ms":11.7948,"dur_verifier_total_ns":11794814,"dur_verify_compute_ms":0.0024,"dur_verify_compute_ns":2424,"meta_verification_result":true,"t_get_signatures_finished":1782561871203,"t_get_signatures_start":1782561871201,"t_ready_for_evaluation_received":1782561871139,"t_result_sent":1782561871203,"t_verifier_finished":1782561871213,"t_verifier_start":1782561871201,"t_verify_compute_finished":1782561871203,"t_verify_compute_start":1782561871203},{"attestation_id":"attestation6ccc20e797c9e9f5","dur_send_result_call_ms":9.8774,"dur_send_result_call_ns":9877437,"dur_signatures_fetch_ms":1.6954,"dur_signatures_fetch_ns":1695422,"dur_verifier_reaction_ms":70.6155,"dur_verifier_reaction_ns":70615537,"dur_verifier_total_ms":11.5965,"dur_verifier_total_ns":11596521,"dur_verify_compute_ms":0.0011,"dur_verify_compute_ns":1054,"meta_verification_result":true,"t_get_signatures_finished":1782561871216,"t_get_signatures_start":1782561871215,"t_ready_for_evaluation_received":1782561871144,"t_result_sent":1782561871216,"t_verifier_finished":1782561871226,"t_verifier_start":1782561871215,"t_verify_compute_finished":1782561871216,"t_verify_compute_start":1782561871216}],"oracle":[]}
