{"participant":"robot7","clock":"unix_epoch","time_unit":"ms","t_start":1775818301616,"t_end":1775818421971,"stopped":true,"last_write_ms":1775818415032,"prover":[{"attestation_id":"attestation7758183019116","dur_prover_e2e_ms":5155.0857,"dur_prover_e2e_ns":5155085689,"dur_prover_total_ms":5466.6818,"dur_prover_total_ns":5466681780,"dur_send_evidence_call_ms":9.9967,"dur_send_evidence_call_ns":9996700,"t_evidence_sent":1775818301931,"t_prover_finished":1775818307088,"t_prover_start":1775818301622,"t_result_received":1775818307086},{"attestation_id":"attestation7758183129850","dur_prover_e2e_ms":4494.2739,"dur_prover_e2e_ns":4494273936,"dur_prover_total_ms":4696.9404,"dur_prover_total_ns":4696940387,"dur_send_evidence_call_ms":10.7119,"dur_send_evidence_call_ns":10711934,"t_evidence_sent":1775818312633,"t_prover_finished":1775818317131,"t_prover_start":1775818312434,"t_result_received":1775818317127},{"attestation_id":"attestation7758183237705","dur_prover_e2e_ms":5437.3784,"dur_prover_e2e_ns":5437378422,"dur_prover_total_ms":5952.065,"dur_prover_total_ns":5952064960,"dur_send_evidence_call_ms":86.2036,"dur_send_evidence_call_ns":86203631,"t_evidence_sent":1775818323648,"t_prover_finished":1775818329087,"t_prover_start":1775818323135,"t_result_received":1775818329085},{"attestation_id":"attestation7758183347146","dur_prover_e2e_ms":4645.2482,"dur_prover_e2e_ns":4645248151,"dur_prover_total_ms":4947.6488,"dur_prover_total_ns":4947648766,"dur_send_evidence_call_ms":9.1527,"dur_send_evidence_call_ns":9152725,"t_evidence_sent":1775818334450,"t_prover_finished":1775818339099,"t_prover_start":1775818334152,"t_result_received":1775818339096},{"attestation_id":"attestation7758183456141","dur_prover_e2e_ms":5889.606,"dur_prover_e2e_ns":5889606034,"dur_prover_total_ms":6074.6824,"dur_prover_total_ns":6074682364,"dur_send_evidence_call_ms":10.0506,"dur_send_evidence_call_ns":10050633,"t_evidence_sent":1775818345138,"t_prover_finished":1775818351029,"t_prover_start":1775818344954,"t_result_received":1775818351028},{"attestation_id":"attestation7758183553835","dur_prover_e2e_ms":5331.2281,"dur_prover_e2e_ns":5331228058,"dur_prover_total_ms":5458.3291,"dur_prover_total_ns":5458329139,"dur_send_evidence_call_ms":9.2742,"dur_send_evidence_call_ns":9274161,"t_evidence_sent":1775818355766,"t_prover_finished":1775818361099,"t_prover_start":1775818355640,"t_result_received":1775818361097},{"attestation_id":"attestation7758183663649","dur_prover_e2e_ms":4594.6642,"dur_prover_e2e_ns":4594664219,"dur_prover_total_ms":4801.4949,"dur_prover_total_ns":4801494943,"dur_send_evidence_call_ms":13.3907,"dur_send_evidence_call_ns":13390716,"t_evidence_sent":1775818366538,"t_prover_finished":1775818371135,"t_prover_start":1775818366333,"t_result_received":1775818371132},{"attestation_id":"attestation7758183773917","dur_prover_e2e_ms":5774.6202,"dur_prover_e2e_ns":5774620249,"dur_prover_total_ms":5992.478,"dur_prover_total_ns":5992478005,"dur_send_evidence_call_ms":10.7385,"dur_send_evidence_call_ns":10738545,"t_evidence_sent":1775818377259,"t_prover_finished":1775818383035,"t_prover_start":1775818377042,"t_result_received":1775818383033},{"attestation_id":"attestation7758183873017","dur_prover_e2e_ms":5221.8138,"dur_prover_e2e_ns":5221813793,"dur_prover_total_ms":5345.9265,"dur_prover_total_ns":5345926522,"dur_send_evidence_call_ms":58.5781,"dur_send_evidence_call_ns":58578088,"t_evidence_sent":1775818387881,"t_prover_finished":1775818393107,"t_prover_start":1775818387761,"t_result_received":1775818393103},{"attestation_id":"attestation7758183983118","dur_prover_e2e_ms":4242.7493,"dur_prover_e2e_ns":4242749292,"dur_prover_total_ms":4714.3439,"dur_prover_total_ns":4714343879,"dur_send_evidence_call_ms":11.7835,"dur_send_evidence_call_ns":11783491,"t_evidence_sent":1775818398852,"t_prover_finished":1775818403098,"t_prover_start":1775818398383,"t_result_received":1775818403095},{"attestation_id":"attestation7758184091388","dur_prover_e2e_ms":5470.0895,"dur_prover_e2e_ns":5470089452,"dur_prover_total_ms":5638.1191,"dur_prover_total_ns":5638119066,"dur_send_evidence_call_ms":10.1031,"dur_send_evidence_call_ns":10103131,"t_evidence_sent":1775818409560,"t_prover_finished":1775818415032,"t_prover_start":1775818409394,"t_result_received":1775818415030}],"verifier":[{"attestation_id":"attestation7758182914670","dur_send_result_call_ms":16.1281,"dur_send_result_call_ns":16128144,"dur_signatures_fetch_ms":3.5652,"dur_signatures_fetch_ns":3565193,"dur_verifier_reaction_ms":4.1612,"dur_verifier_reaction_ns":4161246,"dur_verifier_total_ms":19.75,"dur_verifier_total_ns":19750049,"dur_verify_compute_ms":0.0006,"dur_verify_compute_ns":589,"meta_verification_result":true,"t_get_signatures_finished":1775818301637,"t_get_signatures_start":1775818301634,"t_ready_for_evaluation_received":1775818301629,"t_result_sent":1775818301637,"t_verifier_finished":1775818301653,"t_verifier_start":1775818301634,"t_verify_compute_finished":1775818301637,"t_verify_compute_start":1775818301637},{"attestation_id":"attestation7758183013895","dur_send_result_call_ms":9.483,"dur_send_result_call_ns":9483013,"dur_signatures_fetch_ms":1.415,"dur_signatures_fetch_ns":1415043,"dur_verifier_reaction_ms":1.9558,"dur_verifier_reaction_ns":1955803,"dur_verifier_total_ms":10.9477,"dur_verifier_total_ns":10947654,"dur_verify_compute_ms":0.0006,"dur_verify_compute_ns":585,"meta_verification_result":true,"t_get_signatures_finished":1775818305072,"t_get_signatures_start":1775818305071,"t_ready_for_evaluation_received":1775818305069,"t_result_sent":1775818305072,"t_verifier_finished":1775818305082,"t_verifier_start":1775818305071,"t_verify_compute_finished":1775818305072,"t_verify_compute_start":1775818305072},{"attestation_id":"attestation7758183123129","dur_send_result_call_ms":13.2633,"dur_send_result_call_ns":13263289,"dur_signatures_fetch_ms":4.2107,"dur_signatures_fetch_ns":4210731,"dur_verifier_reaction_ms":3.2164,"dur_verifier_reaction_ns":3216380,"dur_verifier_total_ms":17.5629,"dur_verifier_total_ns":17562942,"dur_verify_compute_ms":0.0006,"dur_verify_compute_ns":576,"meta_verification_result":true,"t_get_signatures_finished":1775818315273,"t_get_signatures_start":1775818315268,"t_ready_for_evaluation_received":1775818315265,"t_result_sent":1775818315273,"t_verifier_finished":1775818315286,"t_verifier_start":1775818315268,"t_verify_compute_finished":1775818315273,"t_verify_compute_start":1775818315273},{"attestation_id":"attestation7758183236682","dur_send_result_call_ms":13.6372,"dur_send_result_call_ns":13637198,"dur_signatures_fetch_ms":2.0748,"dur_signatures_fetch_ns":2074754,"dur_verifier_reaction_ms":2.2446,"dur_verifier_reaction_ns":2244641,"dur_verifier_total_ms":15.7589,"dur_verifier_total_ns":15758856,"dur_verify_compute_ms":0.0006,"dur_verify_compute_ns":553,"meta_verification_result":true,"t_get_signatures_finished":1775818327200,"t_get_signatures_start":1775818327197,"t_ready_for_evaluation_received":1775818327195,"t_result_sent":1775818327200,"t_verifier_finished":1775818327213,"t_verifier_start":1775818327197,"t_verify_compute_finished":1775818327200,"t_verify_compute_start":1775818327200},{"attestation_id":"attestation7758183337017","dur_send_result_call_ms":37.5836,"dur_send_result_call_ns":37583584,"dur_signatures_fetch_ms":45.3071,"dur_signatures_fetch_ns":45307146,"dur_verifier_reaction_ms":2.3141,"dur_verifier_reaction_ns":2314100,"dur_verifier_total_ms":82.9654,"dur_verifier_total_ns":82965397,"dur_verify_compute_ms":0.0006,"dur_verify_compute_ns":620,"meta_verification_result":true,"t_get_signatures_finished":1775818337131,"t_get_signatures_start":1775818337086,"t_ready_for_evaluation_received":1775818337084,"t_result_sent":1775818337131,"t_verifier_finished":1775818337169,"t_verifier_start":1775818337086,"t_verify_compute_finished":1775818337131,"t_verify_compute_start":1775818337131},{"attestation_id":"attestation7758183443829","dur_send_result_call_ms":16.0864,"dur_send_result_call_ns":16086362,"dur_signatures_fetch_ms":1.0511,"dur_signatures_fetch_ns":1051117,"dur_verifier_reaction_ms":3.0125,"dur_verifier_reaction_ns":3012452,"dur_verifier_total_ms":17.2023,"dur_verifier_total_ns":17202322,"dur_verify_compute_ms":0.0005,"dur_verify_compute_ns":507,"meta_verification_result":true,"t_get_signatures_finished":1775818347161,"t_get_signatures_start":1775818347160,"t_ready_for_evaluation_received":1775818347157,"t_result_sent":1775818347161,"t_verifier_finished":1775818347177,"t_verifier_start":1775818347160,"t_verify_compute_finished":1775818347161,"t_verify_compute_start":1775818347161},{"attestation_id":"attestation7758183545431","dur_send_result_call_ms":9.7165,"dur_send_result_call_ns":9716499,"dur_signatures_fetch_ms":1.7429,"dur_signatures_fetch_ns":1742922,"dur_verifier_reaction_ms":2.489,"dur_verifier_reaction_ns":2488997,"dur_verifier_total_ms":11.5304,"dur_verifier_total_ns":11530407,"dur_verify_compute_ms":0.0006,"dur_verify_compute_ns":641,"meta_verification_result":true,"t_get_signatures_finished":1775818357178,"t_get_signatures_start":1775818357176,"t_ready_for_evaluation_received":1775818357173,"t_result_sent":1775818357178,"t_verifier_finished":1775818357187,"t_verifier_start":1775818357176,"t_verify_compute_finished":1775818357178,"t_verify_compute_start":1775818357178},{"attestation_id":"attestation7758183669234","dur_send_result_call_ms":79.0346,"dur_send_result_call_ns":79034582,"dur_signatures_fetch_ms":1.795,"dur_signatures_fetch_ns":1795027,"dur_verifier_reaction_ms":4.6409,"dur_verifier_reaction_ns":4640854,"dur_verifier_total_ms":80.8968,"dur_verifier_total_ns":80896788,"dur_verify_compute_ms":0.0006,"dur_verify_compute_ns":636,"meta_verification_result":true,"t_get_signatures_finished":1775818369152,"t_get_signatures_start":1775818369150,"t_ready_for_evaluation_received":1775818369146,"t_result_sent":1775818369152,"t_verifier_finished":1775818369231,"t_verifier_start":1775818369150,"t_verify_compute_finished":1775818369152,"t_verify_compute_start":1775818369152},{"attestation_id":"attestation7758183654756","dur_send_result_call_ms":87.2131,"dur_send_result_call_ns":87213142,"dur_signatures_fetch_ms":2.5528,"dur_signatures_fetch_ns":2552818,"dur_verifier_reaction_ms":4.3942,"dur_verifier_reaction_ns":4394160,"dur_verifier_total_ms":89.8691,"dur_verifier_total_ns":89869145,"dur_verify_compute_ms":0.0006,"dur_verify_compute_ns":607,"meta_verification_result":true,"t_get_signatures_finished":1775818371144,"t_get_signatures_start":1775818371141,"t_ready_for_evaluation_received":1775818371137,"t_result_sent":1775818371144,"t_verifier_finished":1775818371231,"t_verifier_start":1775818371141,"t_verify_compute_finished":1775818371144,"t_verify_compute_start":1775818371144},{"attestation_id":"attestation7758183772686","dur_send_result_call_ms":9.6292,"dur_send_result_call_ns":9629237,"dur_signatures_fetch_ms":1.2728,"dur_signatures_fetch_ns":1272842,"dur_verifier_reaction_ms":2.0556,"dur_verifier_reaction_ns":2055574,"dur_verifier_total_ms":11,"dur_verifier_total_ns":10999975,"dur_verify_compute_ms":0.0005,"dur_verify_compute_ns":490,"meta_verification_result":true,"t_get_signatures_finished":1775818381146,"t_get_signatures_start":1775818381145,"t_ready_for_evaluation_received":1775818381143,"t_result_sent":1775818381146,"t_verifier_finished":1775818381156,"t_verifier_start":1775818381145,"t_verify_compute_finished":1775818381146,"t_verify_compute_start":1775818381146},{"attestation_id":"attestation7758183875376","dur_send_result_call_ms":9.5489,"dur_send_result_call_ns":9548937,"dur_signatures_fetch_ms":1.7542,"dur_signatures_fetch_ns":1754185,"dur_verifier_reaction_ms":2.859,"dur_verifier_reaction_ns":2859015,"dur_verifier_total_ms":11.3507,"dur_verifier_total_ns":11350701,"dur_verify_compute_ms":0.0009,"dur_verify_compute_ns":862,"meta_verification_result":true,"t_get_signatures_finished":1775818391288,"t_get_signatures_start":1775818391286,"t_ready_for_evaluation_received":1775818391283,"t_result_sent":1775818391288,"t_verifier_finished":1775818391298,"t_verifier_start":1775818391286,"t_verify_compute_finished":1775818391288,"t_verify_compute_start":1775818391288},{"attestation_id":"attestation7758183986295","dur_send_result_call_ms":12.5792,"dur_send_result_call_ns":12579241,"dur_signatures_fetch_ms":1.8243,"dur_signatures_fetch_ns":1824326,"dur_verifier_reaction_ms":2.5871,"dur_verifier_reaction_ns":2587090,"dur_verifier_total_ms":14.4811,"dur_verifier_total_ns":14481119,"dur_verify_compute_ms":0.0005,"dur_verify_compute_ns":515,"meta_verification_result":true,"t_get_signatures_finished":1775818401150,"t_get_signatures_start":1775818401148,"t_ready_for_evaluation_received":1775818401145,"t_result_sent":1775818401150,"t_verifier_finished":1775818401162,"t_verifier_start":1775818401148,"t_verify_compute_finished":1775818401150,"t_verify_compute_start":1775818401150},{"attestation_id":"attestation7758184096840","dur_send_result_call_ms":13.0131,"dur_send_result_call_ns":13013147,"dur_signatures_fetch_ms":1.8424,"dur_signatures_fetch_ns":1842435,"dur_verifier_reaction_ms":4.1233,"dur_verifier_reaction_ns":4123258,"dur_verifier_total_ms":14.9263,"dur_verifier_total_ns":14926324,"dur_verify_compute_ms":0.0005,"dur_verify_compute_ns":546,"meta_verification_result":true,"t_get_signatures_finished":1775818413174,"t_get_signatures_start":1775818413172,"t_ready_for_evaluation_received":1775818413168,"t_result_sent":1775818413174,"t_verifier_finished":1775818413187,"t_verifier_start":1775818413172,"t_verify_compute_finished":1775818413174,"t_verify_compute_start":1775818413174}],"oracle":[]}
