{"participant":"robot29","clock":"unix_epoch","time_unit":"ms","t_start":1779390670358,"t_end":1779390790951,"stopped":true,"last_write_ms":1779390777224,"prover":[{"attestation_id":"attestation592492177e5dda62","dur_prover_e2e_ms":6746.62,"dur_prover_e2e_ns":6746620012,"dur_prover_total_ms":6757.4315,"dur_prover_total_ns":6757431499,"dur_send_evidence_call_ms":14.5071,"dur_send_evidence_call_ns":14507072,"t_evidence_sent":1779390670367,"t_prover_finished":1779390677116,"t_prover_start":1779390670359,"t_result_received":1779390677114},{"attestation_id":"attestation2e1a178fb659bd1e","dur_prover_e2e_ms":6323.55,"dur_prover_e2e_ns":6323550034,"dur_prover_total_ms":6339.3204,"dur_prover_total_ns":6339320396,"dur_send_evidence_call_ms":11.794,"dur_send_evidence_call_ns":11794042,"t_evidence_sent":1779390690878,"t_prover_finished":1779390697208,"t_prover_start":1779390690868,"t_result_received":1779390697202},{"attestation_id":"attestationf55be08f36f9b92d","dur_prover_e2e_ms":9800.314,"dur_prover_e2e_ns":9800313971,"dur_prover_total_ms":9811.2083,"dur_prover_total_ns":9811208255,"dur_send_evidence_call_ms":10.9225,"dur_send_evidence_call_ns":10922532,"t_evidence_sent":1779390711388,"t_prover_finished":1779390721190,"t_prover_start":1779390711379,"t_result_received":1779390721188},{"attestation_id":"attestation00c0ad0dd26618b3","dur_prover_e2e_ms":5287.8442,"dur_prover_e2e_ns":5287844197,"dur_prover_total_ms":5298.0147,"dur_prover_total_ns":5298014662,"dur_send_evidence_call_ms":12.6204,"dur_send_evidence_call_ns":12620448,"t_evidence_sent":1779390731899,"t_prover_finished":1779390737188,"t_prover_start":1779390731890,"t_result_received":1779390737186},{"attestation_id":"attestation7713043c7e5af4cb","dur_prover_e2e_ms":4296.9296,"dur_prover_e2e_ns":4296929578,"dur_prover_total_ms":4314.4878,"dur_prover_total_ns":4314487828,"dur_send_evidence_call_ms":13.8378,"dur_send_evidence_call_ns":13837841,"t_evidence_sent":1779390772921,"t_prover_finished":1779390777224,"t_prover_start":1779390772910,"t_result_received":1779390777218}],"verifier":[{"attestation_id":"attestationead22f8a389f6d1f","dur_send_result_call_ms":36.2941,"dur_send_result_call_ns":36294102,"dur_signatures_fetch_ms":3.8028,"dur_signatures_fetch_ns":3802793,"dur_verifier_reaction_ms":7.1345,"dur_verifier_reaction_ns":7134475,"dur_verifier_total_ms":40.113,"dur_verifier_total_ns":40113044,"dur_verify_compute_ms":0.0006,"dur_verify_compute_ns":645,"meta_verification_result":true,"t_get_signatures_finished":1779390695273,"t_get_signatures_start":1779390695269,"t_ready_for_evaluation_received":1779390695262,"t_result_sent":1779390695273,"t_verifier_finished":1779390695309,"t_verifier_start":1779390695269,"t_verify_compute_finished":1779390695273,"t_verify_compute_start":1779390695273},{"attestation_id":"attestation5f6e758661434af7","dur_send_result_call_ms":46.4123,"dur_send_result_call_ns":46412293,"dur_signatures_fetch_ms":8.5075,"dur_signatures_fetch_ns":8507474,"dur_verifier_reaction_ms":40.9212,"dur_verifier_reaction_ns":40921181,"dur_verifier_total_ms":54.9299,"dur_verifier_total_ns":54929862,"dur_verify_compute_ms":0.0009,"dur_verify_compute_ns":889,"meta_verification_result":true,"t_get_signatures_finished":1779390695318,"t_get_signatures_start":1779390695310,"t_ready_for_evaluation_received":1779390695269,"t_result_sent":1779390695318,"t_verifier_finished":1779390695365,"t_verifier_start":1779390695310,"t_verify_compute_finished":1779390695318,"t_verify_compute_start":1779390695318},{"attestation_id":"attestation31c0a93d2325c32b","dur_send_result_call_ms":23.8627,"dur_send_result_call_ns":23862654,"dur_signatures_fetch_ms":10.2558,"dur_signatures_fetch_ns":10255799,"dur_verifier_reaction_ms":15.46,"dur_verifier_reaction_ns":15459985,"dur_verifier_total_ms":34.1602,"dur_verifier_total_ns":34160177,"dur_verify_compute_ms":0.0019,"dur_verify_compute_ns":1866,"meta_verification_result":true,"t_get_signatures_finished":1779390717364,"t_get_signatures_start":1779390717353,"t_ready_for_evaluation_received":1779390717338,"t_result_sent":1779390717364,"t_verifier_finished":1779390717388,"t_verifier_start":1779390717353,"t_verify_compute_finished":1779390717364,"t_verify_compute_start":1779390717364},{"attestation_id":"attestation56b78f10fe21f94c","dur_send_result_call_ms":31.9866,"dur_send_result_call_ns":31986600,"dur_signatures_fetch_ms":5.1619,"dur_signatures_fetch_ns":5161871,"dur_verifier_reaction_ms":35.2147,"dur_verifier_reaction_ns":35214745,"dur_verifier_total_ms":37.176,"dur_verifier_total_ns":37175991,"dur_verify_compute_ms":0.002,"dur_verify_compute_ns":2021,"meta_verification_result":true,"t_get_signatures_finished":1779390717394,"t_get_signatures_start":1779390717389,"t_ready_for_evaluation_received":1779390717353,"t_result_sent":1779390717394,"t_verifier_finished":1779390717426,"t_verifier_start":1779390717389,"t_verify_compute_finished":1779390717394,"t_verify_compute_start":1779390717394},{"attestation_id":"attestatione50806cb19332bd4","dur_send_result_call_ms":31.1579,"dur_send_result_call_ns":31157902,"dur_signatures_fetch_ms":6.7625,"dur_signatures_fetch_ns":6762451,"dur_verifier_reaction_ms":19.1768,"dur_verifier_reaction_ns":19176849,"dur_verifier_total_ms":37.9586,"dur_verifier_total_ns":37958573,"dur_verify_compute_ms":0.0012,"dur_verify_compute_ns":1210,"meta_verification_result":true,"t_get_signatures_finished":1779390737413,"t_get_signatures_start":1779390737406,"t_ready_for_evaluation_received":1779390737387,"t_result_sent":1779390737413,"t_verifier_finished":1779390737444,"t_verifier_start":1779390737406,"t_verify_compute_finished":1779390737413,"t_verify_compute_start":1779390737413},{"attestation_id":"attestation4f33a91c8d8d45f3","dur_send_result_call_ms":34.4742,"dur_send_result_call_ns":34474157,"dur_signatures_fetch_ms":18.9128,"dur_signatures_fetch_ns":18912765,"dur_verifier_reaction_ms":38.5634,"dur_verifier_reaction_ns":38563448,"dur_verifier_total_ms":53.4129,"dur_verifier_total_ns":53412878,"dur_verify_compute_ms":0.0024,"dur_verify_compute_ns":2399,"meta_verification_result":true,"t_get_signatures_finished":1779390737464,"t_get_signatures_start":1779390737445,"t_ready_for_evaluation_received":1779390737406,"t_result_sent":1779390737464,"t_verifier_finished":1779390737498,"t_verifier_start":1779390737445,"t_verify_compute_finished":1779390737464,"t_verify_compute_start":1779390737464},{"attestation_id":"attestation7532cc44d2a9cd5d","dur_send_result_call_ms":15.8305,"dur_send_result_call_ns":15830463,"dur_signatures_fetch_ms":4.4048,"dur_signatures_fetch_ns":4404783,"dur_verifier_reaction_ms":5.3353,"dur_verifier_reaction_ns":5335269,"dur_verifier_total_ms":20.2884,"dur_verifier_total_ns":20288382,"dur_verify_compute_ms":0.0025,"dur_verify_compute_ns":2480,"meta_verification_result":true,"t_get_signatures_finished":1779390757186,"t_get_signatures_start":1779390757182,"t_ready_for_evaluation_received":1779390757176,"t_result_sent":1779390757186,"t_verifier_finished":1779390757202,"t_verifier_start":1779390757182,"t_verify_compute_finished":1779390757186,"t_verify_compute_start":1779390757186}],"oracle":[]}
