{"participant":"robot1","clock":"unix_epoch","time_unit":"ms","t_start":1782334619001,"t_end":1782334739140,"stopped":true,"last_write_ms":1782334734038,"prover":[{"attestation_id":"attestation7ba084a5f7f6fcf6","dur_prover_e2e_ms":5076.1796,"dur_prover_e2e_ns":5076179576,"dur_prover_total_ms":5088.9549,"dur_prover_total_ns":5088954933,"dur_send_evidence_call_ms":6.5027,"dur_send_evidence_call_ns":6502689,"t_evidence_sent":1782334619022,"t_prover_finished":1782334624100,"t_prover_start":1782334619011,"t_result_received":1782334624098},{"attestation_id":"attestation539c30b6cfe07da5","dur_prover_e2e_ms":5072.5498,"dur_prover_e2e_ns":5072549777,"dur_prover_total_ms":5088.8679,"dur_prover_total_ns":5088867914,"dur_send_evidence_call_ms":7.6859,"dur_send_evidence_call_ns":7685888,"t_evidence_sent":1782334629038,"t_prover_finished":1782334634112,"t_prover_start":1782334629023,"t_result_received":1782334634110},{"attestation_id":"attestation94e86073f4a7478b","dur_prover_e2e_ms":5071.7551,"dur_prover_e2e_ns":5071755121,"dur_prover_total_ms":5086.8919,"dur_prover_total_ns":5086891912,"dur_send_evidence_call_ms":8.2207,"dur_send_evidence_call_ns":8220654,"t_evidence_sent":1782334639053,"t_prover_finished":1782334644126,"t_prover_start":1782334639039,"t_result_received":1782334644124},{"attestation_id":"attestation0b067b8277247c8d","dur_prover_e2e_ms":5083.1695,"dur_prover_e2e_ns":5083169528,"dur_prover_total_ms":5091.9168,"dur_prover_total_ns":5091916778,"dur_send_evidence_call_ms":18.4967,"dur_send_evidence_call_ns":18496695,"t_evidence_sent":1782334649062,"t_prover_finished":1782334654146,"t_prover_start":1782334649054,"t_result_received":1782334654145},{"attestation_id":"attestation1a7baafd9653f627","dur_prover_e2e_ms":5075.954,"dur_prover_e2e_ns":5075954034,"dur_prover_total_ms":5087.9723,"dur_prover_total_ns":5087972262,"dur_send_evidence_call_ms":7.827,"dur_send_evidence_call_ns":7827025,"t_evidence_sent":1782334659072,"t_prover_finished":1782334664151,"t_prover_start":1782334659063,"t_result_received":1782334664148},{"attestation_id":"attestationa0b09fbc1b6f7661","dur_prover_e2e_ms":5069.8918,"dur_prover_e2e_ns":5069891825,"dur_prover_total_ms":5081.8001,"dur_prover_total_ns":5081800106,"dur_send_evidence_call_ms":11.8295,"dur_send_evidence_call_ns":11829489,"t_evidence_sent":1782334669085,"t_prover_finished":1782334674156,"t_prover_start":1782334669074,"t_result_received":1782334674155},{"attestation_id":"attestation13daa4a8ec8b4d0c","dur_prover_e2e_ms":5071.4784,"dur_prover_e2e_ns":5071478421,"dur_prover_total_ms":5082.8708,"dur_prover_total_ns":5082870833,"dur_send_evidence_call_ms":8.6548,"dur_send_evidence_call_ns":8654845,"t_evidence_sent":1782334679095,"t_prover_finished":1782334684169,"t_prover_start":1782334679086,"t_result_received":1782334684167},{"attestation_id":"attestationa89173422fc56c35","dur_prover_e2e_ms":5083.1611,"dur_prover_e2e_ns":5083161095,"dur_prover_total_ms":5096.6575,"dur_prover_total_ns":5096657465,"dur_send_evidence_call_ms":8.7571,"dur_send_evidence_call_ns":8757135,"t_evidence_sent":1782334689108,"t_prover_finished":1782334694193,"t_prover_start":1782334689096,"t_result_received":1782334694191},{"attestation_id":"attestationdaa925ba9c046a7a","dur_prover_e2e_ms":5080.5791,"dur_prover_e2e_ns":5080579057,"dur_prover_total_ms":5090.0562,"dur_prover_total_ns":5090056217,"dur_send_evidence_call_ms":10.6399,"dur_send_evidence_call_ns":10639902,"t_evidence_sent":1782334699117,"t_prover_finished":1782334704199,"t_prover_start":1782334699109,"t_result_received":1782334704198},{"attestation_id":"attestationb10696c8c7d57961","dur_prover_e2e_ms":5085.0963,"dur_prover_e2e_ns":5085096331,"dur_prover_total_ms":5095.1665,"dur_prover_total_ns":5095166451,"dur_send_evidence_call_ms":12.4941,"dur_send_evidence_call_ns":12494149,"t_evidence_sent":1782334709125,"t_prover_finished":1782334714212,"t_prover_start":1782334709117,"t_result_received":1782334714210},{"attestation_id":"attestation2b99c7302d9b6b93","dur_prover_e2e_ms":5074.9633,"dur_prover_e2e_ns":5074963306,"dur_prover_total_ms":5089.6774,"dur_prover_total_ns":5089677414,"dur_send_evidence_call_ms":7.6257,"dur_send_evidence_call_ns":7625672,"t_evidence_sent":1782334719140,"t_prover_finished":1782334724216,"t_prover_start":1782334719126,"t_result_received":1782334724215},{"attestation_id":"attestationc84a777ed8aa3e58","dur_prover_e2e_ms":4885.7365,"dur_prover_e2e_ns":4885736497,"dur_prover_total_ms":4897.0762,"dur_prover_total_ns":4897076184,"dur_send_evidence_call_ms":10.0801,"dur_send_evidence_call_ns":10080138,"t_evidence_sent":1782334729151,"t_prover_finished":1782334734038,"t_prover_start":1782334729141,"t_result_received":1782334734037}],"verifier":[{"attestation_id":"attestationdd5efbcbbc891587","dur_send_result_call_ms":9.5956,"dur_send_result_call_ns":9595588,"dur_signatures_fetch_ms":2.0025,"dur_signatures_fetch_ns":2002513,"dur_verifier_reaction_ms":2.8809,"dur_verifier_reaction_ns":2880913,"dur_verifier_total_ms":11.6144,"dur_verifier_total_ns":11614433,"dur_verify_compute_ms":0.0007,"dur_verify_compute_ns":736,"meta_verification_result":true,"t_get_signatures_finished":1782334622077,"t_get_signatures_start":1782334622075,"t_ready_for_evaluation_received":1782334622072,"t_result_sent":1782334622077,"t_verifier_finished":1782334622087,"t_verifier_start":1782334622075,"t_verify_compute_finished":1782334622077,"t_verify_compute_start":1782334622077},{"attestation_id":"attestationfd0909617c8b5fc2","dur_send_result_call_ms":12.0935,"dur_send_result_call_ns":12093526,"dur_signatures_fetch_ms":3.2113,"dur_signatures_fetch_ns":3211298,"dur_verifier_reaction_ms":3.5714,"dur_verifier_reaction_ns":3571419,"dur_verifier_total_ms":15.3204,"dur_verifier_total_ns":15320398,"dur_verify_compute_ms":0.0008,"dur_verify_compute_ns":808,"meta_verification_result":true,"t_get_signatures_finished":1782334632240,"t_get_signatures_start":1782334632237,"t_ready_for_evaluation_received":1782334632234,"t_result_sent":1782334632240,"t_verifier_finished":1782334632252,"t_verifier_start":1782334632237,"t_verify_compute_finished":1782334632240,"t_verify_compute_start":1782334632240},{"attestation_id":"attestation78c71348af6217ef","dur_send_result_call_ms":11.28,"dur_send_result_call_ns":11280036,"dur_signatures_fetch_ms":2.2655,"dur_signatures_fetch_ns":2265534,"dur_verifier_reaction_ms":16.1872,"dur_verifier_reaction_ns":16187185,"dur_verifier_total_ms":13.5648,"dur_verifier_total_ns":13564820,"dur_verify_compute_ms":0.0013,"dur_verify_compute_ns":1338,"meta_verification_result":true,"t_get_signatures_finished":1782334632256,"t_get_signatures_start":1782334632253,"t_ready_for_evaluation_received":1782334632237,"t_result_sent":1782334632256,"t_verifier_finished":1782334632267,"t_verifier_start":1782334632253,"t_verify_compute_finished":1782334632256,"t_verify_compute_start":1782334632256},{"attestation_id":"attestation1b55a94a716d98fb","dur_send_result_call_ms":14.2777,"dur_send_result_call_ns":14277715,"dur_signatures_fetch_ms":2.8511,"dur_signatures_fetch_ns":2851058,"dur_verifier_reaction_ms":6.7877,"dur_verifier_reaction_ns":6787700,"dur_verifier_total_ms":17.1593,"dur_verifier_total_ns":17159262,"dur_verify_compute_ms":0.0019,"dur_verify_compute_ns":1912,"meta_verification_result":true,"t_get_signatures_finished":1782334642191,"t_get_signatures_start":1782334642188,"t_ready_for_evaluation_received":1782334642181,"t_result_sent":1782334642191,"t_verifier_finished":1782334642205,"t_verifier_start":1782334642188,"t_verify_compute_finished":1782334642191,"t_verify_compute_start":1782334642191},{"attestation_id":"attestationa706e07f2d0c549e","dur_send_result_call_ms":7.9154,"dur_send_result_call_ns":7915407,"dur_signatures_fetch_ms":2.4006,"dur_signatures_fetch_ns":2400572,"dur_verifier_reaction_ms":17.8977,"dur_verifier_reaction_ns":17897683,"dur_verifier_total_ms":10.3302,"dur_verifier_total_ns":10330189,"dur_verify_compute_ms":0.0008,"dur_verify_compute_ns":756,"meta_verification_result":true,"t_get_signatures_finished":1782334642209,"t_get_signatures_start":1782334642206,"t_ready_for_evaluation_received":1782334642188,"t_result_sent":1782334642209,"t_verifier_finished":1782334642216,"t_verifier_start":1782334642206,"t_verify_compute_finished":1782334642209,"t_verify_compute_start":1782334642209},{"attestation_id":"attestation2be427416c82d059","dur_send_result_call_ms":9.7253,"dur_send_result_call_ns":9725341,"dur_signatures_fetch_ms":2.4879,"dur_signatures_fetch_ns":2487873,"dur_verifier_reaction_ms":3.6347,"dur_verifier_reaction_ns":3634726,"dur_verifier_total_ms":12.2302,"dur_verifier_total_ns":12230217,"dur_verify_compute_ms":0.0012,"dur_verify_compute_ns":1217,"meta_verification_result":true,"t_get_signatures_finished":1782334652141,"t_get_signatures_start":1782334652138,"t_ready_for_evaluation_received":1782334652135,"t_result_sent":1782334652141,"t_verifier_finished":1782334652151,"t_verifier_start":1782334652138,"t_verify_compute_finished":1782334652141,"t_verify_compute_start":1782334652141},{"attestation_id":"attestation558b04e59e8a913b","dur_send_result_call_ms":10.9242,"dur_send_result_call_ns":10924247,"dur_signatures_fetch_ms":1.6575,"dur_signatures_fetch_ns":1657466,"dur_verifier_reaction_ms":3.3941,"dur_verifier_reaction_ns":3394146,"dur_verifier_total_ms":12.6075,"dur_verifier_total_ns":12607491,"dur_verify_compute_ms":0.0006,"dur_verify_compute_ns":631,"meta_verification_result":true,"t_get_signatures_finished":1782334662096,"t_get_signatures_start":1782334662095,"t_ready_for_evaluation_received":1782334662091,"t_result_sent":1782334662096,"t_verifier_finished":1782334662107,"t_verifier_start":1782334662095,"t_verify_compute_finished":1782334662096,"t_verify_compute_start":1782334662096},{"attestation_id":"attestation6eb3eb63c2672f9b","dur_send_result_call_ms":8.3628,"dur_send_result_call_ns":8362754,"dur_signatures_fetch_ms":1.8688,"dur_signatures_fetch_ns":1868814,"dur_verifier_reaction_ms":3.5106,"dur_verifier_reaction_ns":3510582,"dur_verifier_total_ms":10.275,"dur_verifier_total_ns":10274965,"dur_verify_compute_ms":0.0017,"dur_verify_compute_ns":1738,"meta_verification_result":true,"t_get_signatures_finished":1782334662118,"t_get_signatures_start":1782334662117,"t_ready_for_evaluation_received":1782334662113,"t_result_sent":1782334662118,"t_verifier_finished":1782334662127,"t_verifier_start":1782334662116,"t_verify_compute_finished":1782334662118,"t_verify_compute_start":1782334662118},{"attestation_id":"attestation9cfec6449355e409","dur_send_result_call_ms":6.1154,"dur_send_result_call_ns":6115377,"dur_signatures_fetch_ms":1.9817,"dur_signatures_fetch_ns":1981729,"dur_verifier_reaction_ms":3.4427,"dur_verifier_reaction_ns":3442685,"dur_verifier_total_ms":8.1195,"dur_verifier_total_ns":8119500,"dur_verify_compute_ms":0.0007,"dur_verify_compute_ns":670,"meta_verification_result":true,"t_get_signatures_finished":1782334672078,"t_get_signatures_start":1782334672076,"t_ready_for_evaluation_received":1782334672073,"t_result_sent":1782334672078,"t_verifier_finished":1782334672084,"t_verifier_start":1782334672076,"t_verify_compute_finished":1782334672078,"t_verify_compute_start":1782334672078},{"attestation_id":"attestation0f132aef133865a1","dur_send_result_call_ms":9.7299,"dur_send_result_call_ns":9729947,"dur_signatures_fetch_ms":2.7354,"dur_signatures_fetch_ns":2735355,"dur_verifier_reaction_ms":3.4893,"dur_verifier_reaction_ns":3489347,"dur_verifier_total_ms":12.4943,"dur_verifier_total_ns":12494261,"dur_verify_compute_ms":0.0019,"dur_verify_compute_ns":1864,"meta_verification_result":true,"t_get_signatures_finished":1782334692187,"t_get_signatures_start":1782334692185,"t_ready_for_evaluation_received":1782334692181,"t_result_sent":1782334692187,"t_verifier_finished":1782334692197,"t_verifier_start":1782334692185,"t_verify_compute_finished":1782334692187,"t_verify_compute_start":1782334692187},{"attestation_id":"attestation59fc6356d5c8852e","dur_send_result_call_ms":7.4728,"dur_send_result_call_ns":7472832,"dur_signatures_fetch_ms":2.2736,"dur_signatures_fetch_ns":2273614,"dur_verifier_reaction_ms":13.2693,"dur_verifier_reaction_ns":13269280,"dur_verifier_total_ms":9.763,"dur_verifier_total_ns":9763043,"dur_verify_compute_ms":0.0016,"dur_verify_compute_ns":1630,"meta_verification_result":true,"t_get_signatures_finished":1782334692200,"t_get_signatures_start":1782334692198,"t_ready_for_evaluation_received":1782334692185,"t_result_sent":1782334692200,"t_verifier_finished":1782334692208,"t_verifier_start":1782334692198,"t_verify_compute_finished":1782334692200,"t_verify_compute_start":1782334692200},{"attestation_id":"attestation3008cb6c67cdc7f6","dur_send_result_call_ms":9.3829,"dur_send_result_call_ns":9382862,"dur_signatures_fetch_ms":2.2583,"dur_signatures_fetch_ns":2258325,"dur_verifier_reaction_ms":3.4711,"dur_verifier_reaction_ns":3471144,"dur_verifier_total_ms":11.6729,"dur_verifier_total_ns":11672944,"dur_verify_compute_ms":0.0018,"dur_verify_compute_ns":1822,"meta_verification_result":true,"t_get_signatures_finished":1782334702149,"t_get_signatures_start":1782334702146,"t_ready_for_evaluation_received":1782334702143,"t_result_sent":1782334702149,"t_verifier_finished":1782334702158,"t_verifier_start":1782334702146,"t_verify_compute_finished":1782334702149,"t_verify_compute_start":1782334702149}],"oracle":[]}
