{"participant":"robot4","clock":"unix_epoch","time_unit":"ms","t_start":1775822477313,"t_end":1775822597716,"stopped":true,"last_write_ms":1775822590099,"prover":[{"attestation_id":"attestation7758224776462","dur_prover_e2e_ms":4534.5059,"dur_prover_e2e_ns":4534505937,"dur_prover_total_ms":4790.9041,"dur_prover_total_ns":4790904149,"dur_send_evidence_call_ms":33.0504,"dur_send_evidence_call_ns":33050389,"t_evidence_sent":1775822477570,"t_prover_finished":1775822482107,"t_prover_start":1775822477316,"t_result_received":1775822482105},{"attestation_id":"attestation7758224888497","dur_prover_e2e_ms":5646.2209,"dur_prover_e2e_ns":5646220903,"dur_prover_total_ms":6036.7452,"dur_prover_total_ns":6036745165,"dur_send_evidence_call_ms":13.6905,"dur_send_evidence_call_ns":13690475,"t_evidence_sent":1775822488460,"t_prover_finished":1775822494108,"t_prover_start":1775822488072,"t_result_received":1775822494107},{"attestation_id":"attestation7758224998813","dur_prover_e2e_ms":4630.4791,"dur_prover_e2e_ns":4630479067,"dur_prover_total_ms":5122.4899,"dur_prover_total_ns":5122489902,"dur_send_evidence_call_ms":20.3046,"dur_send_evidence_call_ns":20304628,"t_evidence_sent":1775822499454,"t_prover_finished":1775822504086,"t_prover_start":1775822498963,"t_result_received":1775822504084},{"attestation_id":"attestation7758225109899","dur_prover_e2e_ms":5688.5377,"dur_prover_e2e_ns":5688537710,"dur_prover_total_ms":6099.6659,"dur_prover_total_ns":6099665878,"dur_send_evidence_call_ms":10.9655,"dur_send_evidence_call_ns":10965547,"t_evidence_sent":1775822510369,"t_prover_finished":1775822516059,"t_prover_start":1775822509959,"t_result_received":1775822516057},{"attestation_id":"attestation7758225214943","dur_prover_e2e_ms":4851.2791,"dur_prover_e2e_ns":4851279073,"dur_prover_total_ms":5232.9221,"dur_prover_total_ns":5232922064,"dur_send_evidence_call_ms":14.4925,"dur_send_evidence_call_ns":14492458,"t_evidence_sent":1775822521248,"t_prover_finished":1775822526104,"t_prover_start":1775822520871,"t_result_received":1775822526099},{"attestation_id":"attestation7758225321031","dur_prover_e2e_ms":6008.8639,"dur_prover_e2e_ns":6008863914,"dur_prover_total_ms":6305.9359,"dur_prover_total_ns":6305935896,"dur_send_evidence_call_ms":91.7941,"dur_send_evidence_call_ns":91794072,"t_evidence_sent":1775822532045,"t_prover_finished":1775822538056,"t_prover_start":1775822531750,"t_result_received":1775822538054},{"attestation_id":"attestation7758225424425","dur_prover_e2e_ms":5146.1205,"dur_prover_e2e_ns":5146120480,"dur_prover_total_ms":5531.8436,"dur_prover_total_ns":5531843588,"dur_send_evidence_call_ms":13.6478,"dur_send_evidence_call_ns":13647847,"t_evidence_sent":1775822542932,"t_prover_finished":1775822548079,"t_prover_start":1775822542548,"t_result_received":1775822548078},{"attestation_id":"attestation7758225534022","dur_prover_e2e_ms":4511.428,"dur_prover_e2e_ns":4511427983,"dur_prover_total_ms":4749.0604,"dur_prover_total_ns":4749060401,"dur_send_evidence_call_ms":16.5329,"dur_send_evidence_call_ns":16532881,"t_evidence_sent":1775822553668,"t_prover_finished":1775822558182,"t_prover_start":1775822553433,"t_result_received":1775822558179},{"attestation_id":"attestation7758225645365","dur_prover_e2e_ms":5717.1075,"dur_prover_e2e_ns":5717107518,"dur_prover_total_ms":5886.2049,"dur_prover_total_ns":5886204933,"dur_send_evidence_call_ms":15.1484,"dur_send_evidence_call_ns":15148365,"t_evidence_sent":1775822564335,"t_prover_finished":1775822570057,"t_prover_start":1775822564170,"t_result_received":1775822570053},{"attestation_id":"attestation7758225744598","dur_prover_e2e_ms":5175.7477,"dur_prover_e2e_ns":5175747748,"dur_prover_total_ms":5311.3061,"dur_prover_total_ns":5311306125,"dur_send_evidence_call_ms":12.5223,"dur_send_evidence_call_ns":12522272,"t_evidence_sent":1775822574972,"t_prover_finished":1775822580149,"t_prover_start":1775822574838,"t_result_received":1775822580148},{"attestation_id":"attestation7758225859382","dur_prover_e2e_ms":4234.9598,"dur_prover_e2e_ns":4234959789,"dur_prover_total_ms":4624.7747,"dur_prover_total_ns":4624774668,"dur_send_evidence_call_ms":14.4912,"dur_send_evidence_call_ns":14491210,"t_evidence_sent":1775822585861,"t_prover_finished":1775822590099,"t_prover_start":1775822585474,"t_result_received":1775822590096}],"verifier":[{"attestation_id":"attestation7758224776107","dur_send_result_call_ms":19.3238,"dur_send_result_call_ns":19323761,"dur_signatures_fetch_ms":3.2792,"dur_signatures_fetch_ns":3279198,"dur_verifier_reaction_ms":3.8507,"dur_verifier_reaction_ns":3850713,"dur_verifier_total_ms":22.6648,"dur_verifier_total_ns":22664835,"dur_verify_compute_ms":0.0004,"dur_verify_compute_ns":384,"meta_verification_result":true,"t_get_signatures_finished":1775822480220,"t_get_signatures_start":1775822480217,"t_ready_for_evaluation_received":1775822480213,"t_result_sent":1775822480220,"t_verifier_finished":1775822480240,"t_verifier_start":1775822480217,"t_verify_compute_finished":1775822480220,"t_verify_compute_start":1775822480220},{"attestation_id":"attestation7758224992865","dur_send_result_call_ms":12.1546,"dur_send_result_call_ns":12154615,"dur_signatures_fetch_ms":2.6676,"dur_signatures_fetch_ns":2667590,"dur_verifier_reaction_ms":4.2405,"dur_verifier_reaction_ns":4240534,"dur_verifier_total_ms":14.878,"dur_verifier_total_ns":14878033,"dur_verify_compute_ms":0.0005,"dur_verify_compute_ns":514,"meta_verification_result":true,"t_get_signatures_finished":1775822502169,"t_get_signatures_start":1775822502166,"t_ready_for_evaluation_received":1775822502162,"t_result_sent":1775822502169,"t_verifier_finished":1775822502181,"t_verifier_start":1775822502166,"t_verify_compute_finished":1775822502169,"t_verify_compute_start":1775822502169},{"attestation_id":"attestation7758224985142","dur_send_result_call_ms":11.058,"dur_send_result_call_ns":11058020,"dur_signatures_fetch_ms":1.368,"dur_signatures_fetch_ns":1368026,"dur_verifier_reaction_ms":2.3586,"dur_verifier_reaction_ns":2358601,"dur_verifier_total_ms":12.4786,"dur_verifier_total_ns":12478630,"dur_verify_compute_ms":0.0006,"dur_verify_compute_ns":598,"meta_verification_result":true,"t_get_signatures_finished":1775822504302,"t_get_signatures_start":1775822504300,"t_ready_for_evaluation_received":1775822504298,"t_result_sent":1775822504302,"t_verifier_finished":1775822504313,"t_verifier_start":1775822504300,"t_verify_compute_finished":1775822504302,"t_verify_compute_start":1775822504302},{"attestation_id":"attestation7758225105317","dur_send_result_call_ms":14.7785,"dur_send_result_call_ns":14778521,"dur_signatures_fetch_ms":1.7071,"dur_signatures_fetch_ns":1707079,"dur_verifier_reaction_ms":3.8806,"dur_verifier_reaction_ns":3880579,"dur_verifier_total_ms":16.547,"dur_verifier_total_ns":16546963,"dur_verify_compute_ms":0.0006,"dur_verify_compute_ns":639,"meta_verification_result":true,"t_get_signatures_finished":1775822514341,"t_get_signatures_start":1775822514339,"t_ready_for_evaluation_received":1775822514336,"t_result_sent":1775822514341,"t_verifier_finished":1775822514356,"t_verifier_start":1775822514339,"t_verify_compute_finished":1775822514341,"t_verify_compute_start":1775822514341},{"attestation_id":"attestation7758225203208","dur_send_result_call_ms":9.0678,"dur_send_result_call_ns":9067785,"dur_signatures_fetch_ms":1.0558,"dur_signatures_fetch_ns":1055802,"dur_verifier_reaction_ms":2.4285,"dur_verifier_reaction_ns":2428504,"dur_verifier_total_ms":10.2347,"dur_verifier_total_ns":10234712,"dur_verify_compute_ms":0.0005,"dur_verify_compute_ns":472,"meta_verification_result":true,"t_get_signatures_finished":1775822526233,"t_get_signatures_start":1775822526232,"t_ready_for_evaluation_received":1775822526229,"t_result_sent":1775822526233,"t_verifier_finished":1775822526242,"t_verifier_start":1775822526232,"t_verify_compute_finished":1775822526233,"t_verify_compute_start":1775822526233},{"attestation_id":"attestation7758225303865","dur_send_result_call_ms":24.509,"dur_send_result_call_ns":24508972,"dur_signatures_fetch_ms":8.1786,"dur_signatures_fetch_ns":8178592,"dur_verifier_reaction_ms":50.5759,"dur_verifier_reaction_ns":50575889,"dur_verifier_total_ms":32.7402,"dur_verifier_total_ns":32740207,"dur_verify_compute_ms":0.0006,"dur_verify_compute_ns":611,"meta_verification_result":true,"t_get_signatures_finished":1775822536340,"t_get_signatures_start":1775822536331,"t_ready_for_evaluation_received":1775822536281,"t_result_sent":1775822536340,"t_verifier_finished":1775822536364,"t_verifier_start":1775822536331,"t_verify_compute_finished":1775822536340,"t_verify_compute_start":1775822536340},{"attestation_id":"attestation7758225426610","dur_send_result_call_ms":24.522,"dur_send_result_call_ns":24522048,"dur_signatures_fetch_ms":1.9226,"dur_signatures_fetch_ns":1922624,"dur_verifier_reaction_ms":3.1714,"dur_verifier_reaction_ns":3171432,"dur_verifier_total_ms":26.5176,"dur_verifier_total_ns":26517588,"dur_verify_compute_ms":0.0156,"dur_verify_compute_ns":15615,"meta_verification_result":true,"t_get_signatures_finished":1775822546186,"t_get_signatures_start":1775822546184,"t_ready_for_evaluation_received":1775822546181,"t_result_sent":1775822546186,"t_verifier_finished":1775822546211,"t_verifier_start":1775822546184,"t_verify_compute_finished":1775822546186,"t_verify_compute_start":1775822546186},{"attestation_id":"attestation7758225526369","dur_send_result_call_ms":17.7358,"dur_send_result_call_ns":17735760,"dur_signatures_fetch_ms":1.1687,"dur_signatures_fetch_ns":1168670,"dur_verifier_reaction_ms":4.4571,"dur_verifier_reaction_ns":4457128,"dur_verifier_total_ms":18.9785,"dur_verifier_total_ns":18978450,"dur_verify_compute_ms":0.0006,"dur_verify_compute_ns":596,"meta_verification_result":true,"t_get_signatures_finished":1775822558340,"t_get_signatures_start":1775822558339,"t_ready_for_evaluation_received":1775822558334,"t_result_sent":1775822558340,"t_verifier_finished":1775822558358,"t_verifier_start":1775822558339,"t_verify_compute_finished":1775822558340,"t_verify_compute_start":1775822558340},{"attestation_id":"attestation7758225636282","dur_send_result_call_ms":11.987,"dur_send_result_call_ns":11986996,"dur_signatures_fetch_ms":1.0615,"dur_signatures_fetch_ns":1061473,"dur_verifier_reaction_ms":2.3655,"dur_verifier_reaction_ns":2365467,"dur_verifier_total_ms":13.1579,"dur_verifier_total_ns":13157882,"dur_verify_compute_ms":0.0005,"dur_verify_compute_ns":528,"meta_verification_result":true,"t_get_signatures_finished":1775822568279,"t_get_signatures_start":1775822568278,"t_ready_for_evaluation_received":1775822568276,"t_result_sent":1775822568279,"t_verifier_finished":1775822568291,"t_verifier_start":1775822568278,"t_verify_compute_finished":1775822568279,"t_verify_compute_start":1775822568279},{"attestation_id":"attestation7758225741373","dur_send_result_call_ms":13.927,"dur_send_result_call_ns":13926984,"dur_signatures_fetch_ms":1.6099,"dur_signatures_fetch_ns":1609924,"dur_verifier_reaction_ms":2.4022,"dur_verifier_reaction_ns":2402248,"dur_verifier_total_ms":15.5822,"dur_verifier_total_ns":15582161,"dur_verify_compute_ms":0.0005,"dur_verify_compute_ns":543,"meta_verification_result":true,"t_get_signatures_finished":1775822578185,"t_get_signatures_start":1775822578183,"t_ready_for_evaluation_received":1775822578181,"t_result_sent":1775822578185,"t_verifier_finished":1775822578199,"t_verifier_start":1775822578183,"t_verify_compute_finished":1775822578185,"t_verify_compute_start":1775822578185},{"attestation_id":"attestation7758225842695","dur_send_result_call_ms":12.8199,"dur_send_result_call_ns":12819866,"dur_signatures_fetch_ms":5.8753,"dur_signatures_fetch_ns":5875302,"dur_verifier_reaction_ms":6.6036,"dur_verifier_reaction_ns":6603632,"dur_verifier_total_ms":18.752,"dur_verifier_total_ns":18751954,"dur_verify_compute_ms":0.0006,"dur_verify_compute_ns":602,"meta_verification_result":true,"t_get_signatures_finished":1775822588239,"t_get_signatures_start":1775822588233,"t_ready_for_evaluation_received":1775822588227,"t_result_sent":1775822588239,"t_verifier_finished":1775822588252,"t_verifier_start":1775822588233,"t_verify_compute_finished":1775822588239,"t_verify_compute_start":1775822588239}],"oracle":[]}
