{"participant":"robot45","clock":"unix_epoch","time_unit":"ms","t_start":1782716612374,"t_end":1782716732737,"stopped":true,"last_write_ms":1782716728217,"prover":[{"attestation_id":"attestationfa15d10de103acbc","dur_prover_e2e_ms":9780.713,"dur_prover_e2e_ns":9780713018,"dur_prover_total_ms":9799.5649,"dur_prover_total_ns":9799564872,"dur_send_evidence_call_ms":30.2391,"dur_send_evidence_call_ns":30239060,"t_evidence_sent":1782716612384,"t_prover_finished":1782716622174,"t_prover_start":1782716612375,"t_result_received":1782716622165},{"attestation_id":"attestation0af4928281d36feb","dur_prover_e2e_ms":7735.2547,"dur_prover_e2e_ns":7735254682,"dur_prover_total_ms":7753.9636,"dur_prover_total_ns":7753963639,"dur_send_evidence_call_ms":18.851,"dur_send_evidence_call_ns":18850983,"t_evidence_sent":1782716622398,"t_prover_finished":1782716630139,"t_prover_start":1782716622385,"t_result_received":1782716630133},{"attestation_id":"attestationab9e97a234a561e7","dur_prover_e2e_ms":7734.8387,"dur_prover_e2e_ns":7734838676,"dur_prover_total_ms":7748.721,"dur_prover_total_ns":7748721038,"dur_send_evidence_call_ms":15.8955,"dur_send_evidence_call_ns":15895512,"t_evidence_sent":1782716632410,"t_prover_finished":1782716640147,"t_prover_start":1782716632399,"t_result_received":1782716640145},{"attestation_id":"attestation10e0384032eb741c","dur_prover_e2e_ms":5701.4901,"dur_prover_e2e_ns":5701490064,"dur_prover_total_ms":5712.2577,"dur_prover_total_ns":5712257691,"dur_send_evidence_call_ms":16.9204,"dur_send_evidence_call_ns":16920386,"t_evidence_sent":1782716642421,"t_prover_finished":1782716648124,"t_prover_start":1782716642411,"t_result_received":1782716648122},{"attestation_id":"attestation365d24b51ac1c081","dur_prover_e2e_ms":7742.854,"dur_prover_e2e_ns":7742854037,"dur_prover_total_ms":7756.0814,"dur_prover_total_ns":7756081418,"dur_send_evidence_call_ms":18.5226,"dur_send_evidence_call_ns":18522568,"t_evidence_sent":1782716652431,"t_prover_finished":1782716660177,"t_prover_start":1782716652421,"t_result_received":1782716660174},{"attestation_id":"attestation77197ba442abba0e","dur_prover_e2e_ms":7739.6807,"dur_prover_e2e_ns":7739680711,"dur_prover_total_ms":7753.7608,"dur_prover_total_ns":7753760807,"dur_send_evidence_call_ms":16.119,"dur_send_evidence_call_ns":16118991,"t_evidence_sent":1782716662440,"t_prover_finished":1782716670185,"t_prover_start":1782716662431,"t_result_received":1782716670180},{"attestation_id":"attestationede2206e6473a40b","dur_prover_e2e_ms":7741.592,"dur_prover_e2e_ns":7741591982,"dur_prover_total_ms":7756.8292,"dur_prover_total_ns":7756829230,"dur_send_evidence_call_ms":15.5194,"dur_send_evidence_call_ns":15519384,"t_evidence_sent":1782716672450,"t_prover_finished":1782716680197,"t_prover_start":1782716672440,"t_result_received":1782716680192},{"attestation_id":"attestation82b0132e1e287af0","dur_prover_e2e_ms":5695.4126,"dur_prover_e2e_ns":5695412555,"dur_prover_total_ms":5705.8881,"dur_prover_total_ns":5705888139,"dur_send_evidence_call_ms":14.6136,"dur_send_evidence_call_ns":14613632,"t_evidence_sent":1782716682459,"t_prover_finished":1782716688157,"t_prover_start":1782716682451,"t_result_received":1782716688155},{"attestation_id":"attestation3bdb7b9bfc90d84e","dur_prover_e2e_ms":7733.3638,"dur_prover_e2e_ns":7733363838,"dur_prover_total_ms":7750.1273,"dur_prover_total_ns":7750127277,"dur_send_evidence_call_ms":14.9027,"dur_send_evidence_call_ns":14902695,"t_evidence_sent":1782716692473,"t_prover_finished":1782716700210,"t_prover_start":1782716692459,"t_result_received":1782716700206},{"attestation_id":"attestationd0418f355db14b40","dur_prover_e2e_ms":7730.1649,"dur_prover_e2e_ns":7730164945,"dur_prover_total_ms":7749.0252,"dur_prover_total_ns":7749025215,"dur_send_evidence_call_ms":15.6754,"dur_send_evidence_call_ns":15675446,"t_evidence_sent":1782716702481,"t_prover_finished":1782716710222,"t_prover_start":1782716702473,"t_result_received":1782716710212},{"attestation_id":"attestation277c272596ff6f8b","dur_prover_e2e_ms":7728.9522,"dur_prover_e2e_ns":7728952226,"dur_prover_total_ms":7742.2597,"dur_prover_total_ns":7742259686,"dur_send_evidence_call_ms":15.7247,"dur_send_evidence_call_ns":15724707,"t_evidence_sent":1782716712493,"t_prover_finished":1782716720224,"t_prover_start":1782716712482,"t_result_received":1782716720222},{"attestation_id":"attestation35b55982f36a35bd","dur_prover_e2e_ms":5708.6597,"dur_prover_e2e_ns":5708659746,"dur_prover_total_ms":5723.6191,"dur_prover_total_ns":5723619126,"dur_send_evidence_call_ms":16.4387,"dur_send_evidence_call_ns":16438728,"t_evidence_sent":1782716722502,"t_prover_finished":1782716728217,"t_prover_start":1782716722494,"t_result_received":1782716728211}],"verifier":[],"oracle":[]}
